Workbook
Name bl_no_h: #REF!
Name Ocean_vessel_voyage_no: #REF!

Sheet Sheet2
F7: TSL
F8: TKM
D12: Week number 20: 12th May -18th May
D13: Week number 21: 19th May -25th May
D14: Week number 22: 26th May -1st June
D15: Week number 23: 2nd June -8th June

Sheet New Releases
A1: PO Number

Sheet FCL+Import
A1: Supplier | B1: Category | C1: PO number | D1: Incoterm | E1: Release date | F1: Days Count | G1: POL | H1: POD | I1: Gross Wt | J1: No of Boxes/Pacakages | K1: Vessel | L1: ETD | M1: ETA | N1: SOB | O1: Pre-alert Date | P1: Posi | Q1: Column1 | R1: Column2 | S1: Column3
A2: Taihua Group | B2: IMPORT | C2: HLBU3334881 | D2: CFR | E2: 16/10/2024 | F2: #VALUE! | G2: MUN | H2: RTM | I2: 16000 | J2: 1x 40'HC / Anlieferung Burghausen 02.12.2024 | K2: Seaspan Ganges | L2: 27.10.2024 | M2: 24.11.2024 | P2: 80-0003-411-00 | Q2: HLF 29200550
A3: Taihua Group | B3: IMPORT | C3: HLBU2182927 | D3: CFR | E3: 16/10/2024 | F3: #VALUE! | G3: MUN | H3: RTM | I3: 16000 | J3: 1x 40'HC / Anlieferung Schkopau 04.12.2024 | K3: Seaspan Ganges | L3: 27.10.2024 | M3: 24.11.2024 | P3: 80-0004-411-00 / 80-0005-411-00 | Q3: HLF 25578990
A4: Danieli | B4: TLL | C4: TSL/52026/2400002408 | D4: FOB | E4: 13/11/2024 | F4: #VALUE! | G4: DLC | H4: NSA | I4: 73366 | J4: 7x 40'FR + 1x 40'HC // NOR019 | K4: Margrete Maersk | L4: 30.11.2024 | M4: 23.12.2024 | O4: 12.12.2024 | P4: 22-0036-412-00 | Q4: SFE24250243
A5: Alpine Metal // RFQ no : 623-24-634 | B5: TLL | C5: TSL/54623/2400002634 Lot-1 | D5: FOB | E5: 14/11/2024 | F5: #VALUE! | G5: ANT | H5: VTZ | I5: 12400 | J5: 3x 40'HC | K5: Hy Singapore | L5: 29.11.2024 | M5: 05.01.2025 | O5: 09.12.2024 | P5: 22-0012-412-00 | Q5: YML FHAM0173685
A6: Reel GmbH | B6: NON-TATA | C6: 2406509 | D6: DAP | E6: 15/11/2024 | F6: #VALUE! | G6: SHA | H6: Sharjah | I6: 8344 | J6: 1x40'GP | K6: SYDNEY BRIDGE | L6: 30/11/2024 | M6: 20/12/2024 | O6: 09.12.2024 | P6: 25-0006-412-00 | Q6: SFE24250250A /B
A7: Puyang Refractories // ST00001123 | B7: TSL | C7: TSL/2200057775 | D7: FOB | E7: 27/11/2024 | F7: #VALUE! | G7: DLC | H7: CCU | I7: 204606 | J7: 8x 20'DV | K7: OOCL AMERICA 176S | L7: 09.12.2024 | M7: 05.01.2025 | O7: 18.12.2024 | P7: 32-0014-412-00 | Q7: SFE24250229 // 032E509264
A8: GVA | B8: NON-TATA | D8: INLAND | E8: 13/11/2024 | F8: #VALUE! | G8: SHA | H8: CCU | I8: 30900 | J8: 1 Slagpot | K8: Atlanta Express | L8: 06.12.2024 | M8: 12.01.2025 | O8: - | P8: 25-0009-502-00
A9: Danieli | B9: TLL | C9: TSL/52026/2400002408 | D9: FOB | E9: 19/11/2024 | F9: #VALUE! | G9: QIN | H9: NSA | I9: 11750 | J9: 1x 40'FR / Ref. NOR023 | K9: X-Press Carina | L9: 09.12.2024 | M9: 30.12.2024 | O9: 17.12.2024 | P9: 22-0040-412-00 | Q9: SFE24250246
A10: SMS Group // RFQ no. 459-17 | B10: TLL | C10: TSL/53459/2400002517 | D10: FOB | E10: 28.06.2024 | F10: #VALUE! | G10: HAM | H10: MUM | I10: 83900 | J10: BB 3+1 | K10: Nowowiejski | L10: 10.12.2024 | M10: 18.01.2025 | O10: 19.12.2024 | P10: 22-0035-412-00 | Q10: CP MDSCP240799
A11: SMS | B11: TLL | C11: TSL/53595/2400002529 - Lot 2b | D11: FOB | E11: 11.10.2024 | F11: #VALUE! | G11: HAM | H11: KTP | I11: 62404 | J11: 2x 40'FR(OH) | K11: MEXICO EXPRESS | L11: 11.12.2024 | M11: 13.01.2025 | O11: 13.12.2024 | P11: 27-0002-412-00 | Q11: Ceekay (HL 35132832)
A12: Reel GmbH | B12: NON-TATA | C12: PD0G01321_29238 | D12: CIF | E12: 45607 | F12: 30 | G12: HAM | H12: CCU | I12: 3600 | J12: 1x20'FR (OW OS) | K12: MEXICO EXPRESS | L12: 45608 | M12: 15/01/2025 | O12: 13.12.2024 | P12: 25-0004-412-00 | Q12: Ceekay 24560130
A13: SEOUL ENGG. (RFQ 229-74) | B13: TLL | C13: TSL/54229/2200056174 | D13: FOB | E13: 18.11.2024 | F13: #VALUE! | G13: PUS | H13: CCU | I13: 6630 | J13: 1X20'GP | K13: SITC OSAKA/2432S | L13: 08.12.2024 | M13: 08.01.2025 | O13: 13.12.2024 | P13: 32-0009-412-00 | Q13: Shipped // pre-alert to be sent // FLGSS2412004 // SITPUCC161089G
A14: Bekaert - Balmer | B14: NON-TATA | C14: 4600003466 - Lot 2 | D14: FOB | E14: 19/11/2024 | F14: #VALUE! | G14: ANT | H14: VTZ | J14: 1x20'DV | K14: Mexico Express | L14: 15.12.2024 | M14: 45992 | O14: 16.12.2024 | P14: 25-0005-412-00 | Q14: YML FHAM0172017
A15: Refra 4 | B15: NON-TATA | C15: Gestellung 02.12.2024 / 7 + 9 | D15: CFR | E15: 10.10.2024 | F15: #VALUE! | G15: ANT | H15: VTZ | I15: 41000 | J15: 2x 20'DV | K15: Mexico Express | L15: 15.12.2024 | M15: 12.01.2025 | O15: 16.12.2024 | P15: 25-0008-412-00 | Q15: YML FHAM0172751
A16: Danieli | B16: TLL | C16: TSL/52026/2400002408 | D16: FOB | E16: 19.11.2024 | F16: #VALUE! | G16: LCB | H16: NSA | J16: 1x 40'FR + 5x 40'HC // Ref. NOR022 | K16: YM INTERACTION | L16: 21.12.2024 | M16: 05.01.2025 | O16: 06.01.2025 | P16: 22-0009-501-00 | Q16: OECL / OOCL
A17: Metallon | B17: TSL | C17: TSL/4413088508 | D17: FOB | E17: 27.11.2024 | F17: #VALUE! | G17: TJN | H17: CCU | J17: 4x 40'OT | K17: MSC TRIESTE V.FY451A | L17: 20.12.2024 | M17: 10.01.2025 | O17: 27.12.2024 | P17: 32-0003-501-00 | Q17: SFE24250256 // MEDUYX322322
A18: Alpine Metal | B18: TLL | C18: TSL/54623/2400002634 Lot-2 | D18: FOB | E18: 21/10/2024 | F18: #VALUE! | G18: ANT | H18: VTZ | I18: 40220 | J18: 1x40'FR(IG), 2x40'FR (OW/OH) | K18: YM FOUNTAIN | L18: 26.12.2024 | M18: 22/01/2025 | O18: 02.01.2025 | P18: 22-0011-501-00 | Q18: Ceekay 15126149
A19: Danieli | B19: TLL | C19: TSL/52026/2400002408 | D19: FOB | E19: 18.11.2024 | F19: #VALUE! | G19: GEN | H19: NSA | J19: 1x 40'HC + 1x 20'DV // NOR015 - 3 | K19: Yantian Express | L19: 25.12.2024 | M19: 29.01.2025 | O19: 31.12.2024 | P19: 22-0012-501-00 | Q19: HLF 27522007
A20: Danieli | B20: TLL | C20: TSL/52026/2400002408 | D20: FOB | E20: 18.11.2024 | F20: #VALUE! | G20: GEN | H20: NSA | J20: 40'HCOT(IG) +40'HCOT(OH270) // NOR015 - 1.2 | K20: Yantian Express | L20: 25.12.2024 | M20: 29.01.2025 | O20: 31.12.2024 | P20: 22-0012-501-00 | Q20: HLF 24903357
A21: Danieli | B21: TLL | C21: TSL/52026/2400002408 | D21: FOB | E21: 18.11.2024 | F21: #VALUE! | G21: GEN | H21: NSA | J21: 6x 40'HC // NOR015 - 1.1 | K21: Yantian Express | L21: 25.12.2024 | M21: 29.01.2025 | O21: 31.12.2024 | P21: 22-0012-501-00 | Q21: HLF 90853739
A22: Danieli | B22: TLL | C22: TSL/52026/2400002408 | D22: FOB | E22: 18.11.2024 | F22: #VALUE! | G22: GEN | H22: NSA | J22: 4x 20'OT(IG) // NOR015 - 2.2 | K22: Yantian Express | L22: 25.12.2024 | M22: 29.01.2025 | O22: 31.12.2024 | P22: 22-0012-501-00 | Q22: HLF 12459407
A23: Danieli | B23: TLL | C23: TSL/52026/2400002408 | D23: FOB | E23: 18.11.2024 | F23: #VALUE! | G23: GEN | H23: NSA | J23: 10x 40'HC // NOR015 - 2.1 | K23: Yantian Express | L23: 25.12.2024 | M23: 29.01.2025 | O23: 31.12.2024 | P23: 22-0012-501-00 | Q23: HLF 31816803
A24: Profine | B24: NON-TATA | D24: CIF | E24: 25/11/2024 | F24: 42 | G24: ANT | H24: NSA | J24: 1x40'HC | K24: MSC JOANNA | L24: 45809 | M24: 45690 | O24: 07.01.2025 | P24: 25-0004-501-00 | Q24: MSC 459HA1255411
A25: CPI Vertex | B25: NON-TATA | C25: NL nach Kilgore | D25: CFR | E25: 16.10.2024 | F25: #VALUE! | G25: ANT | H25: HOU | I25: 25600 | J25: 1x 20'OT(IG) | K25: Lucie Schulte | L25: 24.12.2024 | M25: 18.01.2025 | O25: 06.01.2025 | P25: 25-0008-501-00 | Q25: MSK 247572948
A26: Mack Valves // RFQ no : 813-24-666 | B26: TLL | C26: TSL/54813/2400002666 | D26: FOB | E26: 13.11.2024 | F26: #VALUE! | G26: MEL | H26: VTZ | I26: 2740 | J26: 1x20'DV | K26: CMA CGM Tancredi | L26: 05.01.2025 | M26: 18.02.2025 | O26: 08.01.2025 | P26: 22-0028-501-00 | Q26: HL34146253
A27: Tenova | B27: TLL | C27: TSL/52245/2400002415 | D27: FOB | E27: 19.12.2024 | F27: #VALUE! | G27: GEN | H27: NSA | I27: 3674 | J27: 1x20'DV | K27: Hyundai Mars | L27: 16.01.2025 | M27: 20.02.2025 | O27: 21.01.2025 | P27: 22-0029-501-00 | Q27: HMM HAMA38490100
A28: Rupf ATG Casting | B28: Import | C28: CICU8107408 | D28: CFR | E28: 22/12/2024 | F28: #VALUE! | G28: Zhengzhou | H28: HAM | I28: 10646 | J28: 5 cases | K28: WB2024/12/18 | L28: 22.12.2024 | M28: 18.01.2025 | P28: 80-0002-501-00 | Q28: ZIHWB241218LH201
A29: Reissverschluss18 | B29: Import | C29: TWN24110059 | D29: CFR | E29: 18.11.2024 | F29: #VALUE! | G29: KEE | H29: HAM | I29: 3769 | J29: 45 Pkgs | K29: Ever Ace | L29: 16.11.2024 | M29: 08.01.2025 | P29: 80-0001-501-00 | Q29: LSE-890075
A30: Haeusler | B30: NON-TATA | D30: EXW | E30: 45424 | F30: 52 | G30: ANT | H30: VTZ | J30: 1x20'OT, 1x40'OT | K30: RIO GRANDE EXPRESS | L30: 26/01/2025 | M30: 45780 | O30: 30.01.2025 | P30: 25-0003-502-00 | Q30: HL 24857010
A31: ACRE | B31: TLL | C31: TSL/55394/2400002739 | D31: FOB | E31: 19.09.2024 | F31: #VALUE! | G31: TXZ | H31: MAA | I31: 15650 | J31: 2 BB | K31: STAR TYCHE V.MK2461E | L31: 45484 | M31: 27/11/2024 | O31: 19.11.2024 | P31: 27-0003-411-00 | Q31: BBE24250003 // MK2461ETJCHN04
A32: CHINA SHOUGANG // RFQ No :- 318-08 | B32: TLL | C32: TSL/52318/2200053108 | D32: FOB | E32: 05.12.2024 | F32: #VALUE! | G32: TJN | H32: VIZ | I32: 6400 | J32: 1X20/ 6TONS | K32: TS KAOHSIUNG V.24022S | L32: 26.12.2024 | M32: 26.01.2024 | O32: 30.12.2024 | P32: 32-0007-501-00 | Q32: SFE24250271// 800410284386
A33: HEBEI CHENBANG // RFQ no. 290-51 | B33: TLL | C33: TSL/55290/2200057951 | D33: FOB | E33: 14.12.2024 | F33: #VALUE! | G33: QIN | H33: VTZ | I33: 20350 | J33: 1X40'HQ | K33: TS VANCOUVER V.25001W | L33: 06.01.2025 | M33: 23.01.2025 | O33: 08.01.2025 | P33: 32-0009-501-00 | Q33: SFE24250282 // TAOCB24015397
A34: QINYE // UNDER L/C // CRITICAL | B34: TLL | C34: TSL/55036/2200057503 | D34: FOB | E34: 06.12.2024 | F34: #VALUE! | G34: TJN | H34: VTZ | I34: 3865 | J34: 10.11x20FR | K34: SITC BATANGAS V.2502S | L34: 31.12.2024 | M34: 31.01.2025 | O34: 06.01.2025 | P34: 32-0008-501-00 | Q34: SFE24250280 // SITSTXVZ519593
A35: DANIELI | B35: TLL | C35: TSL/52026/2400002408 - NOR026 | D35: FOB | E35: 45870 | F35: #VALUE! | G35: SHA | H35: NSA | I35: 6930 | J35: 1x 20'DV | K35: ONE REPUTATION | L35: 20.01.2025 | M35: 24.02.2025 | O35: 27.01.2025 | P35: 22-0017-502-00 | Q35: SFE24250324
A36: K-ONE // UNDER LC | B36: TLL | C36: TSL/55387/2400002728 | D36: FOB | E36: 24/12/2024 | F36: 38 | G36: PUS | H36: VTZ | I36: 4710 | J36: 1x40'HC | K36: YM WITNESS | L36: 31/01/2025 | M36: 45660 | O36: 04.02.2025 | P36: 32-0001-502-00 | Q36: FLGSS2501006
A37: DANIELI CORUS // RFQ no : 705/24-649 | B37: TLL | C37: TSL/54705/2400002649 - L1 | D37: FOB | E37: 09.01.2025 | F37: #VALUE! | G37: SHA | H37: CCU | I37: 11200 | J37: 2x40'OT | K37: WAN HAI 516 | L37: 01.02.2025 | M37: 20/02/2025 | P37: 32-0002-502-00 | Q37: SFE24250329
A38: Paulwurth - Balmer | B38: NON-TATA | C38: 4130002679 | D38: FOB | E38: 16/12/2024 | F38: 48 | G38: ANT | H38: NSA | I38: 17453 | J38: 1x40'FR, 1x20'DV | K38: VUNG TAU EXPRESS | L38: 45690 | M38: 45872 | O38: 03.02.2025 | P38: 25-0006-502-00 | Q38: Ceekay HL 31706099
A39: SMS GROUP | B39: TLL | C39: TSL/54763/2400002657 - Lot 1.1 | D39: FOB | E39: 28/01/2025 | F39: #VALUE! | G39: HAM | H39: MUM | I39: 17660 | J39: 3 Pcs / BB | K39: CP Atlantic | L39: 30.01.2025 | M39: 15.03.2025 | O39: 10.02.2025 | P39: 22-0028-502-00 | Q39: CP MDSCP250049
A40: TEAMWELL // ST00001212 | B40: TSL | C40: TSL/2200058898 | D40: FOB | E40: 02.01.2025 | F40: #VALUE! | G40: XIN | H40: CCU | I40: 162900 | J40: 9X20'GP | K40: ISARA BHUM | L40: 45749 | M40: 27/01/2025 | O40: 07.02.2025 | P40: 32-0003-502-00 | Q40: SFE24250308 // TSNCB25000219
A41: Bradley | B41: TLL | C41: TSL/53399/2200054879 | D41: FOB | E41: 45601 | F41: #VALUE! | G41: NYC | H41: KTP | I41: 4558.6 | J41: 1x 40'HCOT | K41: Al Safat | L41: 09.02.2025 | M41: 12.04.2025 | O41: 12.02.2025 | P41: 23-0004-502-00 | Q41: MLAC (HL70030166)
A42: Danieli | B42: TLL | C42: TSL/52026/2400002408 - NOR032 | D42: FOB | E42: 45870 | F42: #VALUE! | G42: DLC | H42: NSA | I42: 239680 | J42: 1x 20'DV, 8x40'HC, 15x40'FR (OOG) | K42: STRATFORD | L42: 11.02.2025 | M42: 45750 | O42: 17.02.2025 | P42: 32-0005-502-00 | Q42: SFE24250323 // OOLU2754444840
A43: Danieli | B43: TLL | C43: TSL/52026/2400002408 - NOR033 | D43: FOB | E43: 24/01/2025 | F43: 24 | G43: SHA | H43: NSA | I43: 33321 | J43: 2x20'GP, 2x40'HC | K43: X-PRESS PYXIS V.25002W | L43: 17/02/2025 | M43: 45872 | O43: 24.02.2025 | P43: 32-0006-502-00 | Q43: SFE24250338 // JJCSHNVY500068
A44: Danieli | B44: CombiMill | D44: FOB | E44: 16/01/2025 | F44: #VALUE! | G44: GOT | H44: VTZ | I44: 8050 | J44: 1x 40'FR(OOG) | K44: Bjorg / YM Fountain | L44: 22.02.2025 | M44: 03.05.2025 | O44: 07.03.2025 | P44: 26-0002-503-00 | Q44: Ceekay HL 55116154
A45: Danieli | B45: CombiMill | D45: FOB | E45: 16/01/2025 | F45: #VALUE! | G45: WLM | H45: MUM | I45: 32200 | J45: 1 Pcs / BB | K45: Theben | L45: 20.02.2025 | M45: 07.04.2025 | O45: 07.03.2025 | P45: 26-0001-503-00 | Q45: WW DEIN2006441
A46: DGWL (RFQ no : 575-42) | B46: TLL | C46: TSL/55575/2400002742 | D46: FOB | E46: 25/02/2025 | F46: -3 | G46: HAM | H46: CCU | I46: 5890 | J46: 1x40'FR | K46: Cisnes | L46: 22/02/2025 | M46: 24/04/2025 | O46: 25.02.2025 | P46: 22-0015-503-00 | Q46: Ceekay HL 13882037
A47: TMT | B47: TLL | C47: TSL/55584/2200058496 | D47: EXW | E47: 45840 | F47: #VALUE! | G47: ANT | H47: KAT | I47: 3350 | J47: 1x 20'DV | K47: Cisnes | L47: 24.02.2025 | M47: 31.03.2025 | O47: 28.02.2025 | P47: 22-0017-503-00 | Q47: HL 32728869
A48: Reissverschluss19 | B48: Import | C48: YMJAN209112539 / FTAU1141472 | D48: CFR | E48: 16/12/2024 | F48: #VALUE! | G48: KEE | H48: HAM | I48: 9145 | J48: 1x 20'DV | K48: YM Credibility | L48: 15.12.2024 | M48: 08.02.2025 | O48: 19/02/2025 | P48: 80-0001-502-00 | Q48: LSE-890089
A49: Reissverschluss20 | B49: Import | C49: YMJAN209113295 | D49: CFR | E49: 45992 | F49: 0 | G49: KEE | H49: HAM | I49: 9227 | J49: 1x20'DC | K49: Hamburg Express | L49: 45992 | M49: 15/03/2025 | O49: 17/03/2025 | P49: 80-0001-503-00 | Q49: LSE-890099
A50: Reissverschluss21 | B50: Import | D50: CFR | E50: 45811 | F50: -1 | G50: KHH | H50: HAM | I50: 586 | J50: 1 Pallet | K50: EVER ACE | L50: 45780 | M50: 24/04/2025 | O50: 22/04/2025 | P50: 80-0002-504-00 | Q50: LSE-890110
A51: CPI Vertex | B51: NON-TATA | C51: Gestellung | D51: CFR | E51: 45694 | F51: 1 | G51: ANT | H51: ANG | I51: 32000 | J51: 40'FR(OOG) + 40'HC | K51: Santos Express | L51: 45722 | M51: 15/04/2025 | O51: 14.03.2025 | P51: 25-0010-503-00 | Q51: HL 26100690
A52: DANIELI | B52: TLL | C52: TSL/52026/2400002408 - NOR041 | D52: FOB | E52: 27/02/2025 | F52: 16 | G52: HPH | H52: NSA | I52: 23473 | J52: 3x40'HC | K52: EVER WILL | L52: 15/03/2025 | M52: 45751 | N52: 15/03/2025 | O52: 25.03.2025 | P52: 32-0007-503-00 | Q52: SFE24250354
A53: DANIELI | B53: TLL | C53: TSL/52026/2400002408 - NOR041 | D53: FOB | E53: 27/02/2025 | F53: 19 | G53: HPH | H53: NSA | I53: 29903 | J53: 4x40'OT | K53: WAN HAI 361 | L53: 18/03/2025 | M53: 45934 | N53: 18/03/2025 | O53: 25.03.2025 | P53: 32-0006-503-00 | Q53: SFE24250358
A54: VALJI // ST00001318 | B54: TSL | C54: 2200056643 | D54: FOB | E54: 20/02/2025 | F54: 26 | G54: KOP | H54: VTZ | I54: 19174 | J54: 1x20'OT | K54: MAERSK HANGZHOU | L54: 18/03/2025 | M54: 17/05/2025 | N54: 18/03/2025 | O54: 26/03/2025 | P54: 22-0029-503-00 | Q54: SI25000217
A55: VALJI // ST00001319 | B55: TSL | C55: 2200056643 | D55: FOB | E55: 21/02/2025 | F55: 25 | G55: KOP | H55: VTZ | I55: 19174 | J55: 1x20'OT | K55: MAERSK HANGZHOU | L55: 18/03/2025 | M55: 17/05/2025 | N55: 18/03/2025 | O55: 26/03/2025 | P55: 22-0030-503-00 | Q55: SI25000218
A56: AUSTIN | B56: TLL | C56: TSL/55801/4413418091 | D56: EXW | E56: 45841 | F56: 15 | G56: BTM | H56: CCU | I56: 13949 | J56: 4 pcs | K56: Charter ETA BTM - 20TH.MAR.2025.IAGW WP. | L56: 22/03/2025 | M56: 29/03/2025 | N56: 22/03/2025 | O56: 24/03/2025 | P56: 22-0016-504-00 | Q56: HQ2515BTMVZ001
A57: AUSTIN | B57: TLL | C57: TSL/55800/4413418079 | D57: EXW | E57: 45841 | F57: 15 | G57: BTM | H57: CCU | I57: 13949 | J57: 4 pcs | K57: Charter ETA BTM - 20TH.MAR.2025.IAGW WP. | L57: 22/03/2025 | M57: 29/03/2025 | N57: 22/03/2025 | O57: 24/03/2025 | P57: 22-0019-504-00 | Q57: HQ2515BTMVZ004
A58: AUSTIN (RFQ no : 801-901-DO) | B58: TLL | C58: TSL/55760/4413413430 | D58: EXW | E58: 18/03/2025 | F58: 4 | G58: BTM | H58: CCU | I58: 55796 | J58: 4 pcs | K58: Charter ETA BTM - 20TH.MAR.2025.IAGW WP. | L58: 22/03/2025 | M58: 29/03/2025 | N58: 22/03/2025 | O58: 24/03/2025 | P58: 22-0018-504-00 | Q58: HQ2515BTMVZ003
A59: AUSTIN (RFQ no : 801-901-DO) | B59: TLL | C59: TSL/55750/4413400552 | D59: EXW | E59: 18/03/2025 | F59: 4 | G59: BTM | H59: CCU | I59: 13949 | J59: 1 pc | K59: Charter ETA BTM - 20TH.MAR.2025.IAGW WP. | L59: 22/03/2025 | M59: 29/03/2025 | N59: 22/03/2025 | O59: 24/03/2025 | P59: 22-0017-504-00 | Q59: HQ2515BTMVZ002
A60: AUSTIN (RFQ no : 801-901-DO) | B60: TLL | C60: TSL/55799/4413418078 | D60: EXW | E60: 18/03/2025 | F60: 4 | G60: BTM | H60: CCU | I60: 55796 | J60: 4 pcs | K60: Charter ETA BTM - 20TH.MAR.2025.IAGW WP. | L60: 22/03/2025 | M60: 29/03/2025 | N60: 22/03/2025 | O60: 24/03/2025 | P60: 22-0020-504-00 | Q60: HQ2515BTMVZ005
A61: BUCK MATERIALS // RFQ no. 733-24-655 | B61: TLL | C61: TSL/54733/2400002655 | D61: FOB | E61: 29/01/2025 | F61: 54 | G61: KOP | H61: VTZ | I61: 11300 | J61: 1x40'HC | K61: ITAL WIT / HMM OCEAN | L61: 24/03/2025 | M61: 26/04/2025 | N61: 24/03/2025 | O61: 45720 | P61: 22-0009-504-00 | Q61: HAMA75700000
A62: Salico Hispania S.A. | B62: TLL | C62: TSL/52455/2400002428 | D62: FOB | E62: 20/02/2025 | F62: 37 | G62: GEN | H62: ENN | I62: 117048 | J62: 2 pcs / BB | K62: BAHRI YANBU | L62: 29/03/2025 | M62: 18/05/2025 | N62: 29/03/2025 | O62: 45842 | P62: 22-0021-504-00 | Q62: EGCBY029018
A63: GVA Krefeld GmbH // RFQ no : 341-53 | B63: TLL | C63: TSL/55341/2200058053 | D63: FOB | E63: 27/02/2025 | F63: 34 | G63: SHA | H63: CCU | I63: 94730 | J63: 3 Pcs / BB | K63: GENIUS ACE MK2523E | L63: 45692 | M63: 24/04/2025 | N63: 45692 | O63: 45934 | P63: 32-0005-504-00 | Q63: MK2519ESHAKOL01 / BBE24250004
A64: Profine | B64: NON-TATA | C64: KW12 | D64: CIF | E64: 45841 | F64: 35 | G64: ANT | H64: NSA | J64: 1x40'HC | K64: HYUNDAI TOKYO | L64: 45965 | M64: 30/04/2025 | N64: 45965 | O64: 14/04/2025 | P64: 25-0002-504-00 | Q64: YM FHAM0176992
A65: Kemmlitzer Kaolinwerke | B65: TKM | C65: Gestellung: 31.03.2025 / 8.00Uhr | D65: EXW | E65: 45720 | F65: 9 | G65: HAM | H65: COC | I65: 20000 | J65: 1x 20'DV | K65: Maersk Tukang | L65: 45995 | M65: 26/05/2025 | N65: 45995 | O65: 14/04/2025 | P65: 25-0006-504-00 | Q65: HL 39766131
A66: Primetals | B66: Import | C66: Anlieferung 28.05.2025 | D66: DAP | E66: 17/03/2025 | F66: -22 | G66: GGV | H66: HAM | I66: 14733 | J66: 1x20'DV | K66: MSC SABRINA III | L66: 23/02/2025 | M66: 45934 | P66: 80-0001-505-00 | Q66: MEDUVO545382
A67: BECK U.KALTHEUNER | B67: TSL | C67: TSL/2200059504 / ST00001384 | D67: FOB | E67: 25/03/2025 | F67: 37 | G67: ANT | H67: VTZ | J67: 2x20'DV | K67: HMM OAKLAND | L67: 45662 | M67: 15/06/2025 | N67: 45752 | O67: 45874 | P67: 22-0013-505-00 | Q67: YML FHAM0174047 / FHAM0174048
A68: Bilfinger | B68: TLL | C68: TSL/55406/2200058172 | D68: EXW | E68: 45661 | F68: 34 | G68: HAM | H68: CCU | I68: 6020 | J68: 1x20'OT | K68: Maersk Guayaquil | L68: 45782 | M68: 6/12/2025 (Z25002637872 - Z no. cancelled by Krishna on 23.04) | N68: 45782 | O68: 45874 | P68: 22-0008-505-00 | Q68: Ceekay HL 21468110 (CCU208772- LCL booking cancelled)// MBL NO. CKYHAMCCU74214
A69: Reimbold & Strick | B69: NON-TATA | C69: Gestellung: | D69: CFR | E69: 27/03/2025 | F69: 20 | G69: ANT | H69: KEE | I69: 8920 | J69: 1x20'DC | K69: ONE Intelligence | L69: 16/04/2025 | M69: 45967 | N69: 16/04/2025 | O69: 17/04/2025 | P69: 25-0007-504-00 | Q69: YML FHAM0177702
A70: BECK U.KALTHEUNER | B70: TSL | C70: TSL/2200055861 / ST00001385 | D70: FOB | E70: 25/03/2025 | F70: 53 | G70: ANT | H70: VTZ | I70: 20600 | J70: 1x20'DV | K70: HYUNDAI SHANGHAI | L70: 17/05/2025 | M70: 22/06/2025 | N70: 17/05/2025 | O70: 19/05/2025 | P70: 22-0024-505-00 | Q70: YML FHAM0177863
A71: Danieli | B71: TLL | C71: TSL/52026/2400002408 - NOR050 | D71: FOB | E71: 45995 | F71: 35 | G71: GOA | H71: NSA | I71: 13760 | J71: 1x20'DV,2x40'HC | K71: HYUNDAI COURAGE | L71: 17/05/2025 | M71: 20/06/2025 | N71: 17/05/2025 | O71: 27/05/2025 | P71: 22-0022-505-00 | Q71: HMM HAMA92521000
A72: Danieli | B72: TLL | C72: TSL/52026/2400002408 - NOR051 | D72: FOB | E72: 45995 | F72: 35 | G72: GOA | H72: NSA | I72: 31580 | J72: 1x20'DV,2x40'HC | K72: HYUNDAI COURAGE | L72: 17/05/2025 | M72: 20/06/2025 | N72: 17/05/2025 | O72: 27/05/2025 | P72: 22-0023-505-00 | Q72: HMM HAMA43831600
A73: L&Y ASIA PACIFIC LIMITED | B73: TSL | C73: TSL/2200057729 / ST00001423 | D73: FOB | E73: 45873 | F73: 46 | G73: QZH | H73: CCU | J73: 6x20'DV | K73: MSC DIEGO | L73: 24/05/2025 | M73: 24/06/2025 | N73: 24/05/2025 | O73: 28/05/2025 | P73: 32-0007-506-00 | Q73: SFE25260033 // MEDUKT439495
A74: Paulwurth | B74: NON-TATA | C74: 4130002678 | D74: FOB | E74: 45782 | F74: 24 | G74: ANT | H74: NSA | I74: 33069 | J74: 1x40'FR | K74: MSC CANDICE | L74: 29/05/2025 | M74: 45695 | N74: 30/05/2025 | O74: 45694 | P74: 25-0002-506-00 | Q74: MSC 459HA1359076
A75: Beck u. Kaltheuner GmbH & Co. KG (RFQ no : 303-10) | B75: TLL | C75: NINL/17303/2299870210 | D75: FOB | E75: 15/04/2025 | F75: 47 | G75: ANT | H75: VTZ | I75: 20600 | J75: 1x20'DV | K75: HMM TACOMA | L75: 45663 | M75: 45754 | N75: 31/05/2025 | O75: 45694 | P75: 22-0004-506-00 | Q75: FHAM0178374
A76: Danieli | B76: TLL | C76: TSL/52026/2400002408 - NOR054 | D76: FOB | E76: 14.04.2025 | F76: 43 | G76: BRI | H76: NSA | J76: 4x40'OT | K76: MOLIVA / MSC HAMBURG | L76: 27/05/2025 | M76: 45968 | N76: 27/05/2025 | O76: 16/06/2025 | P76: 22-0013-506-00 | Q76: MSC 459HA1351087
A77: Danieli | B77: TLL | C77: TSL/52026/2400002408 - NOR057 | D77: FOB | E77: 45995 | F77: 56 | G77: GOA | H77: NSA | I77: 6154 | J77: 1x20'DV | K77: HMM GREEN | L77: 45844 | M77: 45937 | N77: 45967 | O77: 45967 | P77: 22-0012-506-00 | Q77: HMM HAMA90149800
A78: Danieli | B78: TLL | C78: TSL/52026/2400002408 - NOR053 | D78: FOB | E78: 25/04/2025 | F78: 43 | G78: GOA | H78: NSA | I78: 4370 | J78: 1x20'DV, 1x40'OT(OH) | K78: HMM GREEN | L78: 45844 | M78: 45937 | N78: 45967 | O78: 45967 | P78: 22-0011-506-00 | Q78: HMM HAMA68580100
A79: Profine | B79: NON-TATA | C79: Gest. 03.06. 08:00 - done | D79: CIF | G79: ANT | H79: NSA | J79: 1x40'HC | K79: SCI DELHI | L79: 45906 | M79: 18/07/2025 | P79: 25-0006-506-00 | Q79: MSC 459HA1371483
A80: MAN Energy | B80: NON-TATA | D80: FOB | E80: 15.04.2025 | G80: HAM | H80: NSA | I80: 6600 | J80: 1x 20'OT(IG) | K80: Savannah Express | L80: 45936 | M80: 23/07/2025 | N80: 16/06/2025 | O80: 16/06/2025 | P80: 25-0007-506-00 | Q80: Ceekay 15661362
A81: CALDERYS | B81: NON-TATA | C81: 4130002871 | D81: FOB | E81: 20/05/2025 | F81: 25 | G81: ANT | H81: NSA | I81: 46500 | J81: 2x40'HC | K81: MSC Vilda X | L81: 14/06/2025 | M81: 27/07/2025 | P81: 25-0010-506-00 | Q81: MSC 459HA1367910
A82: Scholz | B82: NON-TATA | C82: Gest.: 17.06/6.00 u 18.06/6.00 u 9.30 | D82: CFR | G82: ANT | H82: NSA | I82: 48493 | J82: 1x20'OT,1x40'FR,1x40'OT,1x40'HCOT | K82: MSC AAYA | L82: 30.06.2025 | M82: 28.07.2025 | N82: 45664 | O82: 25/07/2025 | P82: 25-0004-507-00 | Q82: MSC 459HA1361468
A83: Scholz 2 | B83: NON-TATA | C83: Gest.: 16.06 / 6.00/9.30 u 17.06/9.30 | D83: CFR | G83: ANT | H83: NSA | J83: 3x 40'OT(IG) | K83: MSC AAYA | L83: 30.06.2025 | M83: 28.07.2025 | P83: 25-0003-507-00 | Q83: MSC 459HA1371673
A84: Kaiser PBT | B84: NON-TATA | C84: Gest: 23.06. 8:00/10:00 / 24.06. 8:00 | D84: CIF | G84: ANT | H84: NSA | J84: 1x 40'OT(IG) + 2x 40'OT(OH) | K84: MSC LISBON | L84: 45723 | M84: 45938 | N84: 45723 | O84: 45968 | P84: 25-0006-507-00 | Q84: MSC 459HA1373571
A85: Danieli | B85: TLL | C85: NOR061 | D85: FOB | E85: 18.06.2025 | G85: GOA | H85: NSA | I85: 2.330,00 | J85: 1x 40'HC | K85: HYUNDAI JUPITER | L85: 45876 | M85: 12.08.2025 | N85: 45876 | O85: 45968 | P85: 22-0031-507-00 | Q85: HMM HAMA17558400
A86: Danieli | B86: TLL | C86: NOR059 | D86: FOB | E86: 18/06/2025 | G86: GOA | H86: NSA | I86: 17.067,00 | J86: 1x 40'HC +1x20 box | K86: HYUNDAI JUPITER | L86: 45876 | M86: 12.08.2025 | N86: 45876 | O86: 45968 | P86: 22-0032-507-00 | Q86: HMM HAMA42425700
A87: CPI Vertex | B87: NON-TATA | C87: Nachlauf nach Plano, TX | D87: CFR | E87: 12.06.2025 | G87: TLN | H87: HOU | I87: 2500 | J87: 1x 20'DV | K87: Elbwaive / Maersk Ohio | L87: 45907 | M87: 09.08.2025 | P87: 25-0009-507-00 | Q87: HL 56804270
A88: Delsey | B88: NON-TATA | C88: Routing by TKM China | D88: FOB | E88: 13.06.2025 | G88: LEH | H88: NSA | I88: 18000 | J88: 2x 40'HC | K88: HAMMONIA BALTICA | L88: 45968 | M88: 20.08.2025 | P88: 25-0014-507-00 | Q88: HL 92955316
A89: Benhil | B89: NON-TATA | C89: pickup MLPT 26.06.2025 | D89: CFR | G89: ANT | H89: MUN | J89: 1x40'FR(OH) | K89: MSC Pamela | L89: 14/07/2025 | M89: 29.08.2025 | N89: 14/07/2025 | O89: 16/07/2025 | P89: 25-0010-507-00 | Q89: MSC 459HA1383055
A90: TMT | B90: TLL | C90: NINL/17288/2299870163 | D90: FOB | E90: 45997 | F90: 33 | G90: ANT | H90: VTZ | I90: 9600 | J90: 1x40'HC | K90: ONE RECOGNITION | L90: 15/07/2025 | M90: 31.08.2025 | N90: 15/07/2025 | O90: 16/07/2025 | P90: 22-0033-507-00 | Q90: YML FHAM0180064
A91: Wuxi Veco Technology Co., Ltd | B91: TLL | C91: TBD/2232/2400002697 | D91: FOB | E91: 30/06/2025 | F91: 17 | G91: SHA | H91: CCU | I91: 1920 | J91: 1x 20'GP | K91: SITC SHUNDE V.2512S | L91: 17/07/2025 | M91: 45785 | N91: 17/07/2025 | O91: 22/07/2025 | P91: 32-0010-507-00 | Q91: SFE252600071 // SITGSHCCAS0089
A92: Minteq | B92: NON-TATA | C92: Gestellung am 18.07/8.00 | D92: CFR | E92: 25/06/2025 | F92: 36 | G92: ANT | H92: ENN | I92: 7500 | J92: 1x 40'HC | K92: MSC VALERIA | L92: 31/07/2025 | M92: 31.08.2025 | N92: 31/07/2025 | O92: 45665 | P92: 25-0010-508-00 | Q92: MSC 459HA1391877
A93: Metallon | B93: TLL | C93: TSL/56357/2200059895 | D93: FOB | E93: 45665 | F93: 18 | G93: TJN | H93: VTZ | I93: 11214 | J93: 2x40'HC | K93: XIN QING DAO | L93: 19/08/2025 | M93: 16/09/2025 | N93: 19/08/2025 | O93: 25/08/2025 | P93: 32-0014-508-00 | Q93: SFE25260093 / TSNCB25004364
A94: Refra | B94: NON-TATA | C94: 4300039347 | D94: CFR | E94: 22/07/2025 | F94: 33 | G94: ANT | H94: VTZ | I94: 49200 | J94: 2x20'GP | K94: MSC LEIGH | L94: 24/08/2025 | M94: 45726 | N94: 24/08/2025 | O94: 26/08/2025 | P94: 25-0002-509-00 | Q94: MSC 459HA1408546
A95: TSL UK | B95: TLL | C95: TSL/56606/2200060298 | D95: FCA | E95: 22/07/2025 | F95: 35 | G95: LGP | H95: VTZ | I95: 27660 | J95: 1x40'HC | K95: Maersk San Clemente | L95: 26/08/2025 | M95: 45910 | N95: 26/08/2025 | O95: 27/08/2025 | P95: 22-0019-509-00 | Q95: HL 14742615
A96: Refra | B96: NON-TATA | C96: 4300039383 | D96: CFR | E96: 45816 | F96: 19 | G96: DLC | H96: MAA | I96: 73511 | J96: 3x20'GP | K96: XIN CHI WAN | L96: 25/08/2025 | M96: 45910 | N96: 25/08/2025 | O96: 28/08/2025 | P96: 25-0006-509-00 | Q96: SFE25260095 / 032F507496
A97: Refra | B97: NON-TATA | C97: 4300039526 | D97: CFR | E97: 45816 | F97: 19 | G97: BCN | H97: BUE | I97: 11825 | J97: 1x20'GP | K97: COLOMBIA EXPRESS | L97: 25/08/2025 | M97: 19/09/2025 | N97: 25/08/2025 | O97: 25/08/2025 | P97: 25-0018-508-00 | Q97: CF BCNOE15132 / MSK 258006490
A98: Profine | B98: NON-TATA | C98: Gestellung 02.09.2025 / 7.00 | D98: CIF | E98: 45816 | F98: 34 | G98: ANT | H98: NSA | I98: 25000 | J98: 1x 40'HC | K98: ONE REINFORCEMENT | L98: 45909 | M98: 20/10/2025 | N98: 45909 | O98: 45939 | P98: 25-0007-509-00 | Q98: YML FHAM0181566
A99: Paul Wurth | B99: TLL | C99: TSL/56040/2200059256 | D99: FOB | E99: 21/08/2025 | F99: 19 | G99: TJN | H99: CCU | I99: 3600 | J99: BB | K99: SKY HEIGHT | L99: 45909 | M99: 45940 | N99: 45909 | O99: 19/09/2025 | P99: 32-0008-509-00 | Q99: BBE25260002 / SK37XGKT034
A100: Planet Cast | B100: NON-TATA | C100: Gestellung: 22.09. 07/09/11; 23.09. 07/09:00 | D100: FCA | E100: 45939 | F100: 21 | G100: HAM | H100: MUN(TGD) | J100: 5x40'HC | K100: MSC AAYA | L100: 45667 | M100: 19/11/2025 | N100: 45667 | O100: 14/10/2025 | P100: 25-0003-510-00 | Q100: MSC 459HA1440148
...

Sheet FCL+Import Completed
A1: Supplier | B1: Category | C1: PO number | D1: Incoterm | E1: Release date | F1: Days Count | G1: POL | H1: POD | I1: Gross Wt | J1: No of Boxes/Pacakages | K1: Remarks | L1: ETD | M1: ETA | N1: Pre-alert Date | O1: Posi | P1: Column1
A2: Coroplast | C2: TKM Mum nominated | D2: EXW | E2: 43899 | G2: Ham | H2: Nsa | I2: 1115 | J2: 3 pcs | K2: Edison / etd 31.03.2020 | N2: 43925
A3: Coroplast | C3: TKM Mum nominated | D3: EXW | E3: 43899 | G3: Ham | H3: Nsa | I3: 530 | J3: 1 pcs | K3: Edison / etd 31.03.2020 | N3: 43925
A4: Coroplast | C4: TKM Mum nominated | D4: EXW | E4: 43901 | G4: Ham | H4: Nsa | I4: 415 | J4: 1 pcs | K4: Edison / etd 31.03.2020 | N4: 43925
A5: Beka | C5: TSL/2200039874 | D5: FOB | E5: 43902 | G5: Ant | H5: Vtz | I5: 41200 | J5: 2x20' | K5: MSC Maria Saveria / etd 05.04.2020 | N5: 43937
A6: CMI(BSA) | C6: TSL42795/2400002029-DCC03 | D6: FOB | E6: 43886 | G6: Gen | H6: Vtz | I6: 6196 | J6: 1x20'OT(ig) | K6: Ain Snan / etd 05.04.2020 | N6: 43930
A7: CMI(BSA) | C7: TSL/42794/2400002033-DCC03 | D7: FOB | E7: 43886 | G7: Gen | H7: Vtz | I7: 6196 | J7: 1x20'OT(ig) | K7: Ain Snan / etd 05.04.2020 | N7: 43930
A8: Irizar Forge | C8: TSL/44425/2200042530 | D8: EXW | E8: 43899 | G8: Val | H8: CCU | I8: 1756 | J8: 4 pcs | K8: Talos / etd 04.04.2020 | N8: 43937
A9: Irizar Forge | C9: TSL/44165/2200042152 | D9: EXW | E9: 43899 | G9: Val | H9: CCU | I9: 674 | J9: 1 pcs | K9: Talos / etd 04.04.2020 | N9: 43937
A10: Irizar Forge | C10: TSL/44165/2200042152 | D10: EXW | E10: 43899 | G10: Val | H10: CCU | I10: 1566 | J10: 2 pcs | K10: Talos / etd 04.04.2020 | N10: 43937
A11: NKM | C11: CFR | D11: CFR | E11: 43889 | G11: Ham | H11: Nsa | I11: 60000 | J11: 4x40'HC | K11: MSC Ruby / etd 09.04.2020 | N11: 43932
A12: LeLong Vietnam | C12: Agent Nominated Import | D12: CFR | E12: 43931 | G12: Vung Tau | H12: Ham | I12: 40774 | J12: 2x20'DV | K12: ONE Cygnus / ETA 10.04.2020 | N12: 43935
A13: Vesuvius | C13: TSL/2200042890 + 2200043940 | D13: FOB | E13: 43906 | G13: Ant | H13: Vtz | I13: 20560 | J13: 1x40'HC | K13: YM Fountain / etd 11.04.2020 | N13: 43937
... A24: Wheelwash | C24: TSL/45732/2200044263 | D24: EXW | E24: 43943 | G24: Lon | H24: CCU | I24: 700 | J24: 1 pcs | K24: Madrid Bridge / etd 27.04.2020 | N24: 43951
A25: Reimbold | D25: CFR | E25: 43943 | G25: Ham | H25: NSA | I25: 6168 | J25: 6 pcs | K25: Erving / etd 01.05.2020 | N25: 43951
A26: Beka | C26: TSL/2200043787 | D26: FOB | G26: Ant | H26: Hal | I26: 26919 | J26: 1x40'HC, 1x20'DV | K26: Conti Everest / etd 26.04.2020 | N26: 43949
A27: CMI | C27: TSL/42795/2400002029-DCC05 | D27: FOB | E27: 43901 | G27: Gen | H27: Vtz | I27: 112880 | J27: 10x40'HC, 1x20'DV | K27: Thalassa Elpida / etd 28.04.2020 | N27: 43951
A28: CMI | C28: TSL/42793/2400002034-DCC08 | D28: FOB | E28: 43901 | G28: Gen | H28: Vtz | I28: 19170 | J28: 2x40'HC | K28: Thalassa Elpida / etd 28.04.2020 | N28: 43951
A29: Hilger Trading | C29: CFR | D29: CFR | E29: 04.03.20.20 | G29: Ham | H29: Yok | I29: 6000 | J29: 1x40'HC | K29: Bazan / etd 30.04.2020
A30: Z&J | C30: TSL/44136/2200042106 | D30: FOB | E30: 43924 | G30: Ant | H30: CCU | I30: 18141 | J30: 1x40'FR(oog) | K30: Xin Yan Tai / etd 27.04.2020 | N30: 43955
A31: Vesuvius | C31: TSL/2200044155 | D31: FOB | E31: 43909 | G31: Ant | H31: CCU | I31: 60000 | J31: 1x20'DV | K31: Al Safat / etd 09.05.2020 | N31: 43963
A32: Vesuvius | C32: TSL/2200040375 | D32: FOB | E32: 43909 | G32: Ant | H32: CCU | I32: 60000 | J32: 1x40'HC, 1x20'DV | K32: Al Safat / etd 09.05.2020 | N32: 43963
A33: Wheelwash | C33: TSL/45332/2400002164 | D33: FOB | E33: 43924 | G33: Fxt | H33: CCU | I33: 11500 | J33: 1x40'OT(ig) | K33: CS Galaxy / etd 24.04.2020 | N33: 43965
A34: Coroplast | D34: EXW | E34: 43952 | G34: Ham | H34: NSA | I34: 1660 | J34: 5 pcs | K34: Erving / etd 01.05.2020 | N34: 43955
A35: Imerys | C35: TSL/2200041161 | D35: FOB | E35: 43935 | G35: Ant | H35: CCU | I35: 90000 | J35: 4x40'HC | K35: Al Safat / etd 04.05.2020 | N35: 43957
A36: CMI | C36: TSL/42794/2400002033-DCC04 | D36: FOB | E36: 43886 | G36: Ant | H36: Vtz | I36: 3100 | J36: 1x20'DC | K36: Xin Yan Tai / etd 02.05.2020 | N36: 43963
A37: CMI | C37: TSL/42793/2400002034-DCC10 | D37: FOB | E37: 43901 | G37: Ant | H37: Vtz | I37: 11000 | J37: 1x40'FR(oog) | K37: Xin Yan Tai / etd 02.05.2020 | N37: 43963
A38: CMI | C38: TSL/42793/2400002034-DCC07 | D38: FOB | E38: 43946 | G38: Ant | H38: Vtz | I38: 6200 | J38: 1x40'HC | K38: Xin Yan Tai / etd 02.05.2020 | N38: 43963
A39: CMI | C39: TSL/42795/2400002029-DCC06 | D39: FOB | E39: 43901 | G39: Ant | H39: Vtz | I39: 20540 | J39: 1x40'HCOT(oh), 2x40'HC | K39: Xin Yan Tai / etd 02.05.2020 | N39: 43963
A40: CMI | C40: TSL/42793/2400002034-DCC09 | D40: FOB | E40: 43901 | G40: Ant | H40: Vtz | I40: 20540 | J40: 1x40'HCOT(oh), 2x40'HC | K40: Xin Yan Tai / etd 02.05.2020 | N40: 43963
A41: CMI | C41: TSL/42795/2400002029-DCC04 | D41: FOB | E41: 43886 | G41: Ant | H41: Vtz | I41: 3100 | J41: 1x20'DC | K41: Xin Yan Tai / etd 02.05.2020 | N41: 43963
A42: DHM | C42: TSL/45383/2200043405 | D42: EXW | E42: 43945 | G42: Odessa | H42: CCU | I42: 120 | J42: 1 pcs | K42: Navios Summer / etd 13.05.2020 | N42: 43979
A43: DHM | C43: TSL/45188/2200043579 | D43: EXW | E43: 43945 | G43: Odessa | H43: CCU | I43: 220 | J43: 1 pcs | K43: Navios Summer / etd 13.05.2020 | N43: 43979
A44: DHM | C44: TSL/45319/2200043639 | D44: EXW | E44: 43945 | G44: Odessa | H44: CCU | I44: 265 | J44: 1 pcs | K44: Navios Summer / etd 13.05.2020 | N44: 43979
A45: ASA Drilling | C45: TSL/45479/2200043889 | D45: EXW | E45: 43944 | G45: Lon | H45: CCU | I45: 2256 | J45: 2 pcs | K45: ONE Apus / etd 14.05.2020 | N45: 43965
A46: Bronx | C46: TSL/44982/2200043247 | D46: FOB | E46: 43950 | G46: Lon | H46: CCU | I46: 2370 | J46: 3 pcs | K46: UMM Qarn etd 25.05.2020 | N46: 43979
A47: Reimbold | D47: CFR | E47: 43951 | G47: Ham | H47: NSA | I47: 2576.5 | J47: 3 pcs | K47: Ever Genius / etd 21.05.2020 | N47: 43979
A48: Reimbold | D48: CFR | E48: 43959 | G48: Ham | H48: NSA | I48: 6157 | J48: 6 pcs | K48: Ever Genius / etd 21.05.2020 | N48: 43979
A49: Coroplast | D49: EXW | E49: ? | G49: Ham | H49: NSA | I49: 13 | J49: 1 pcs | K49: Ever Genius / etd 21.05.2020 | N49: 43979
A50: BSA | C50: TSL/45044/2200043375 | D50: FOB | E50: 43909 | G50: Gen | H50: CCU | I50: 2572 | J50: 3 pcs | K50: ONE Millau / etd 18.05.2020 | N50: 43987
A51: Thermocast | C51: TSL/40193/2200036833 | D51: FOB | E51: 43958 | G51: Gen | H51: CCU | I51: 5320 | J51: 4 pcs | K51: ONE Millau / etd 18.05.2020 | N51: 43987
A52: Michelin | C52: TSL/45255/2200043665 | D52: FOB | E52: 43909 | G52: Bio | H52: CCU | I52: 5155 | J52: 1x40'OT(oh) - partload | K52: Baltic Tern / etd 18.05.2020 | N52: 43980
A53: Michelin | C53: TSL/45256/2200043601 | D53: FOB | E53: 43909 | G53: Bio | H53: CCU | I53: 5155 | J53: 1x40'OT(oh) - partload | K53: Baltic Tern / etd 18.05.2020 | N53: 43980
A54: 7Refractories | C54: TSL/2200041175 | D54: FOB | E54: 43950 | G54: Koper | H54: HAL | I54: 10300 | J54: 1x20' | K54: Maersk Hamburg / etd 27.05.2020 | N54: 43985
A55: Kümas | C55: TSL/2200043948 | D55: FOB | E55: ?? | G55: Gem | H55: CCU | I55: 109222 | J55: 5x20' | K55: MSC TINA / etd 25.05.2020 | N55: 43980
A56: BSA | C56: TSL/45070/2200043409 | D56: FOB Genoa | E56: 43971 | G56: Gen | H56: CCU | I56: 1255 | J56: LCL - 1crate 235x99x110cm | K56: JEBELI ALI/ etd 01.06.2020 | N56: 43990
A57: TENOVA | C57: TSL/45323/2200043753 | D57: FOB Genoa | E57: 43972 | G57: GEN | H57: CCU | I57: 3130 | J57: 1x 683x152x67 | K57: JEBELI ALI/ etd 01.06.2020 | N57: 43990
A58: Intermetall | C58: TSL/44980/2200043213 | D58: FOB Genoa | E58: 43974 | G58: GEN | H58: CCU | I58: 1558 | J58: 1 crate - 2,48x70x82cm | K58: JEBELI ALI/ etd 01.06.2020 | N58: 43990
A59: Rothe Erde | C59: TSL/44749/2200042867 | D59: FOB | E59: 43963 | G59: Ham | H59: Vtz | I59: 3250 | K59: “MOL Guardian“ 2021E / etd 03.06.2020 | N59: 43987
A60: PWI | C60: TSL/45398/2200043873 | D60: FOB Shenzhen | E60: 43973 | G60: Shenzhen | H60: CCU | I60: 8114 | J60: 1x20'dc | K60: NORTHERN VOLITION / etd 06.06.2020 | N60: 43992
A61: CMI | C61: TSL/42793/2400002034-DCC11 | D61: FOB | E61: 43930 | G61: Gen | H61: Vtz | I61: 44027 | J61: 3x40'FR, 3x40'HC | K61: Titan / etd 26.05.2020 | N61: 43992
A62: DANA | C62: TSL/45442/2200043846 | D62: EXW Warrington, UK | E62: 43972 | H62: CCU | I62: 605 | J62: LCL - 1 PKG 140x90x110cm | K62: Al Jmeliyah / etd 02.06.20 | O62: 22-0015-006 | P62: finales HBL/MBL kommen nach Zahlungseingang
A63: SARCLAD | C63: TICRC/1542/2200043830 | D63: FCA Sarclad Rotherham UK | E63: 43972 | G63: FXT | H63: Nhava Sheva | I63: 1200 | J63: LCL - 1PKG 130x130x127cmn | K63: Maerks Gibralta / etd 06.06.2020 | O63: 22-0021-006 | P63: finales HBL/MBL kommen nach Zahlungseingang
A64: ESAB | C64: TSL/45396/2200043709 | D64: EXW | E64: 43977 | G64: HOU | H64: CCU | I64: 1222 | J64: 5 | K64: Belita / etd 10.06.2020
A65: SMS | C65: TSL/44222/2200042181 | D65: FOB | G65: HAM | H65: BOM | I65: 61687 | J65: BB | K65: Adam Asnyk / etd 12.06.2020 | O65: 22-0016-006 | P65: HBL bereits bestätigt
A66: Imerys | C66: TSL/2200041161 | D66: FOB | E66: ??? | G66: Ant | H66: CCU | I66: 90000 | J66: 4x40'HC | K66: Taurus / etd 13.06.2020 | O66: 22-0017-006 | P66: prealert machen / HBL Bestätigung fehlt noch
A67: RHT | C67: TSL/45372/2200043728 | D67: FOB Genoa | E67: 43983 | G67: GEN | H67: CCU | I67: 560 | J67: LCL | K67: HAMBURG EXPRESS /etd 14.06.2020
A68: Trucktec | G68: Jebel Ali | H68: Hamburg | I68: 11324 | J68: 1x40'HC - 92 PLT | K68: EDISON / ETA 14.06.20 | O68: 80-0001-006 | P68: Freigabe an Dachser -> siehe Email Entwurf
A69: HASCO | C69: TSBSL/10030/2299900058 | D69: FOB | E69: 43989 | G69: BUS | H69: CCU | I69: 1071 | J69: LCL - 1 Pkg | K69: KMTC Jebel Ali / etd 15.06.2020
A70: Lintern | C70: TSL/45419/2400002173 | D70: EXW | E70: 43973 | G70: LAX | H70: CCU | I70: 1605 | J70: 2 | K70: CMA CGM Chennai / etd 15.06.2020
A71: NORITAKE | C71: TSL/45405/2200043876 | D71: FOB Nagoya | E71: 43980 | G71: NGO | H71: CCU | I71: 1103 | J71: 4 | K71: NYK Fushimi / etd 16.06.2020
A72: NORITAKE | C72: TSL/45263/2200043675 | D72: FOB Nagoya | E72: 43980 | G72: NGO | H72: CCU | I72: 816 | J72: 3 | K72: NYK Fushimi / etd 16.06.2020
A73: NORITAKE | C73: TSL/45277/2200043676 | D73: FOB Nagoya | E73: 43980 | G73: NGO | H73: CCU | I73: 850 | J73: 4 | K73: NYK Fushimi / etd 16.06.2020
A74: Everlasting Valve | C74: TSL/45776/2200044303 | D74: EX Works | E74: 43986 | G74: NYC | H74: CCU | I74: 802 | J74: 1 | K74: Seaspawn Osprey / etd 17.06.2020
A75: Intensiv Filter | D75: CFR | E75: 43991 | G75: HAM | H75: Haiphong | I75: 1171 | J75: 7 Pal | K75: NYK Wren / etd 18.06.2020 | O75: 25-0001-006
A76: Europlast | D76: DDU | E76: 43986 | G76: Ant | H76: JEA | I76: 4180 | J76: 1x20'dc | K76: Al Jasrah / etd 20.06.2020 | P76: Gestellung durch uns (Hapag) -> C-Point/VGM/HBL/MBL
A77: ACRE | C77: TSL/2200043312 | D77: FOB | E77: 43991 | G77: SHA | H77: VIZAG | J77: 6x20' | K77: KMTC Mundra / etd 22.06.2020
A78: BeKa | C78: TSL/2200039873 | D78: FOB | E78: 43987 | G78: ANT | H78: CCU | I78: 40000 | J78: 2x20' | K78: ER Los Angeles / etd 22.06.2020 | P78: wird FOB geliefert -> VGM/HBL/MBL
A79: BeKa | C79: TSL/2200044107 | D79: FOB | E79: 43987 | G79: ANT | H79: VTZ | I79: 40000 | J79: 2x20' | K79: Diaporos / etd 04.07.2020 | P79: wird FOB geliefert -> VGM/HBL/MBL
A80: Benhil | D80: CFR | E80: 2062020 | G80: Ant | H80: NSA | I80: 5550 | J80: 1x40'FR OH | K80: ROME EXPRESS / etd 07.07.2020 | P80: Abholung/Stauen durch uns (MLPT) -> VGM/HBL/MBL
A81: Europlast | D81: DDU | E81: 43963 | G81: Ant | H81: JEA | I81: 20000 | J81: 1x20'dc | K81: APL Chongqing / etd 30.06.2020 | P81: Gestellung durch uns (Hapag) -> C-Point/VGM/HBL/MBL
A82: KOYO | C82: TSL/44746/2200042664 | D82: FOB SIN or JP? | E82: 43983 | G82: SIN | H82: CCU | I82: 2485 | J82: ? | N82: pending
A83: Dalian Huarui Heavy Industry | C83: TSL/2200041959 + TSL/2200041963 + TSL/2200041656 + TSL/2200043327 | H83: CCU | N83: pending
A84: RHI | C84: TSL/2200035612 | D84: FOB | G84: DLC | H84: CCU | I84: 440000 | J84: 325 | K84: 19x20' each 23 ton | N84: pending
A85: FOSSA | C85: TSL/45183/2200043541 | D85: EXW | E85: 43983 | G85: GEN | H85: CCU | I85: 673 | J85: LCL - 1 PKG | K85: New York Express / etd 12.07.2020 | N85: 44034
A86: BeKa | C86: TSL/2200039873 | D86: FOB | E86: 43987 | G86: ANT | H86: CCU | I86: 20000 | J86: 1x20' | K86: YM Fountain / etd 18.07.2020 | N86: 44033 | O86: 22-0023-007
A87: Metallisation | C87: TSL/45798/2200044207 | D87: FCA SUPPLIER | E87: 44013 | G87: London | H87: CCU | I87: 2491 | J87: 3 | K87: booked for sailing 19.07.2020 | N87: 44033
A88: Qunye | C88: TISWD 1185/2200043714 | D88: FOB | E88: 44006 | G88: Shanghai | I88: 21060 | K88: Wan Hai 501 / etd 30.07.2020 | N88: 44032
A89: Hebei Logistics | C89: TSBSL 10061 2299900195 | D89: FOB Shanghai | E89: 44011 | G89: Shanghai | H89: CCU | I89: 545 | K89: Pira Bhum / etd 13.07.2020 | N89: 44034
A90: Cosil | C90: TSL/45731/2200044264 | D90: EXW | E90: 44012 | G90: GEN | H90: CCU | I90: 596 | J90: 1 pcs | K90: New York Express / etd 13.07.2020 | N90: 44029
A91: Beijing Ind | C91: TSBSL/10059/2299900145 | D91: FOB | E91: 44026 | G91: SHA | H91: CCU | I91: 1000 | J91: 1 pcs | K91: ER France / 20.07.2020 | N91: 44041
A92: Timken | C92: TSL/44695/2200042763 | D92: FOB | E92: 44033 | G92: SIN | H92: CCU | I92: 2060 | J92: 4 pcs | K92: Xpress Yamuna / etd 28.07.2020 | N92: 44041
A93: Coroplast | D93: EXW | E93: 44015 | G93: HAM | H93: MUM | I93: 145 | J93: 1 pcs | K93: Madrid Express / etd 17.07.2020 | N93: 44032
A94: PWI | C94: TSL/45315/2200043723 | D94: FOB | E94: 44018 | G94: GEN | H94: CCU | I94: 689 | J94: 1 pcs | K94: New York Express / etd 13.07.2020 | N94: 44029
A95: Reimbold | D95: CFR | E95: 44019 | G95: ANT | H95: BKK | I95: 20500 | J95: 1x20' | K95: Thalassa Mana / etd 18.07.2020 | N95: 44036 | P95: Gestellung am 14.07.2020 / 8.00Uhr
A96: Refra | D96: CFR | E96: 44020 | G96: DLC | H96: NSA | I96: 23000 | J96: 1x20' | K96: Cosco Hamburg / etd 17.07.2020 | N96: 44032 | O96: 25-0008-007
A97: Al Asdeqaa | C97: TSL/45866/2200044373 | D97: FOB | E97: 44011 | G97: XIN | H97: CCU | I97: 820 | J97: 1 pcs | K97: Songa Toscana / etd 19.07.2020 | N97: 44035
A98: RBK | C98: TSBSL/10048/2299900139 | D98: EXW | E98: 44004 | G98: LON | H98: CCU | I98: 1648 | J98: 2 pcs | K98: Afif / etd 26.07.2020 | N98: 44044
A99: TVV | C99: TSL/45576/2200043950 | D99: EXW | E99: 44007 | G99: GEN | H99: CCU | I99: 1300 | J99: 1 pcs | K99: Manhattan Bridge / etd 03.08.2020 | N99: 44060 | P99: 211
A100: Fossa | C100: TSBSL/10074/2299900190 | D100: FOB | E100: 44027 | G100: GEN | H100: CCU | I100: 1269 | J100: 1 pcs | K100: Manhattan Bridge / etd 03.08.2020 | N100: 44060
A101: Fimi | C101: TSBSL/10041/2299900103 | D101: EXW | E101: 44019 | G101: GEN | H101: CCU | I101: 2195 | J101: 2 pcs | K101: Manhattan Bridge / etd 03.08.2020 | N101: 44060 | P101: 204
A102: NTACO | C102: SFE20210059 | D102: DDP | E102: 44019 | G102: NAN | H102: HAM | I102: 10915 | J102: 4x40' | K102: Tonghai / ETA 27.07.2020 | P102: 80-0001-008
A103: NTACO | C103: SFE20210060 | D103: DDP | E103: 44019 | G103: NAN | H103: HAM | I103: 10563 | J103: 4x40' | K103: Tonghai / ETA 27.07.2020 | P103: 80-0002-008
A104: Metallon | C104: TSL/42766/2200040114 | D104: FOB | E104: 44019 | G104: XIN | H104: CCU | I104: 122800 | J104: 5x40'OT(ig) | K104: Merete Maersk / etd 29.07.2020 | N104: 44050
A105: KME | C105: TSL/44337/2200041871 | D105: FOB | E105: 44027 | G105: HAM | H105: CCU | I105: 8440 | J105: 1x20' | K105: MSC Benedetta / etd 30.07.2020 | N105: 44048 | P105: 459HA0251192
A106: Bremskerl | C106: TSL/44858/2200042981 | D106: EXW | E106: 44014 | G106: HAM | H106: CCU | I106: 6840 | J106: 1x20' | K106: MSC Benedetta / etd 30.07.2020 | N106: 44048 | P106: 459HA0250972
A107: Sojitz | C107: TSL/44659/2200042771 | D107: FOB | E107: 44025 | G107: YOK | H107: CCU | I107: 2300 | J107: 1 pcs | K107: NYK Chicago / etd 30.07.2020 | N107: 44048
A108: Outotec | C108: TSL/45189/2200043577 | D108: FOB | E108: 44032 | G108: Busan | H108: CCU | I108: 9440 | J108: 1x20' | K108: MOL Growth / etd 31.07.2020 | N108: 44048
A109: RHI | C109: TSL/2200044044 | D109: FOB | E109: 44020 | G109: DLC | H109: CCU | I109: 421000 | J109: 19x20' | K109: Xin Lian Yun Gang / etd 31.07.2020 | N109: 44050
A110: Gantrex | C110: TSBSL/10010/2299900057 | D110: FOB Antwerp | E110: 43997 | G110: Antwerp | H110: CCU | I110: 3649 | J110: 3 | K110: MSC Benedetta / etd 02.08.2020 | N110: 44054 | P110: 459HA0246426
...

Sheet LCL
A1: Supplier | B1: PO_number | C1: Incoterm | D1: POL | E1: POD | F1: No. of Pieces | G1: Gross Wt. (Kgs) | H1: CBM | I1: Vessel | J1: Release date | K1: Readiness | L1: Days Count (Release Dt. - Readiness Dt.) | M1: Pickup | N1: Arrival at Warehouse | O1: Days Count (Release Dt. - Arrival at WH Dt.) | P1: ETD | Q1: Intended_ETD | R1: Shipped_on_Board | S1: Days Count (Release Dt. - SOB Dt.) | T1: Pre-alert Date | U1: ETA | V1: Z_No | W1: Position_No | X1: HBL | Y1: MBL | Z1: Booking No. | AA1: Remarks | AB1: Additional Remarks | AC1: Pre-alert Remarks | AD1: Pre-Alert saved
A2: GERMANY CCU 1 | AA2: New closing : 11.03.26 // SAC9844 // closing : 11.03.26 // closing : 09.03.26 // closing : 05.03.26 // SAC9828-HMM ROTTERDAM // delayed due to port congestions. | AB2: 91-0002-603-00 // 91-0002-603-01
A3: AHW // Complete Shipment LOT :- 01 // SPA10291 | B3: TSL/57290/2200061379 | C3: FOB | D3: HAM | E3: CCU | F3: 1 | G3: 1220 | H3: 4.59 | I3: ONE RECOMMENDATION V.011E | J3: 46059 | K3: 46062 | L3: =K3-J3 -> 3 | M3: 46066 | N3: 46071 | O3: =IF(ISBLANK(N3)=TRUE,TODAY()-J3,N3-J3) -> 12 | P3: 46103 | Q3: 46099 | R3: 46103 | S3: =IF(ISBLANK(R3)=TRUE,TODAY()-J3,R3-J3) -> 44 | U3: 46166 | V3: Z26001017217 | W3: 22-0006-604-00 | X3: 22-0006-604-00 | Y3: CCU209247 | Z3: CCU209210 | AA3: Shipped - Pre-alert to be sent // Booked on 10.02.26 // Supplier's response & SPA rcvd on 06.02.26 // MRN rcvd on 09.02.26 // The trucking company has advised that the shipment was not loaded due to a transmission error, as the partner did not receive the booking. Loading is now scheduled for 13.02.26, with delivery on 17.02.26 // Rolled to next vessel on 17.02.26 as not reached WH till 16.02.26 // Carrier informed on 19.02.26 that Vessel changed to ONE Innovation due to early arrival of HMM Copenhagen and earlier VGM deadline. New schedule: Closing 24.02, ETD 02.03 // On 20.02.26, the carrier informed that the vessel ONE Innovation is delayed due to port congestion // Rolled to next vessel on 25.02.26 as ONE INNOVATION closed on 25.02.26 // As on 06.03.26 The vessel is delayed due to port congestion, and delays may increase due to the current situation in the Middle East // Carrier informed on 10.03.2026 that cargo has been booked on an earlier vessel ONE RECOMMENDATION // On 17.03.26, the carrier informed that the vessel ONE Recommendation is delayed due to adverse weather conditions on the import-bound leg. The revised ETA at Hamburg is now 22.03.26. | AB3: Non-stackable // We need to charge the supplier for the repacking charges-Euro 1000
A4: Paul Wurth S.A. | B4: TSL/57023/2200060988 | C4: FOB | D4: HAM | E4: CCU | F4: 1 | G4: 2040 | H4: 4.762 | I4: ONE RECOMMENDATION V.011E | J4: 46077 | K4: 46083 | L4: =K4-J4 -> 6 | M4: - | N4: 46086 | O4: =IF(ISBLANK(N4)=TRUE,TODAY()-J4,N4-J4) -> 9 | P4: 46103 | Q4: 46099 | R4: 46103 | S4: =IF(ISBLANK(R4)=TRUE,TODAY()-J4,R4-J4) -> 26 | U4: 46166 | V4: Z26001444561 | W4: 22-0007-604-00 | X4: 22-0007-604-00 | Y4: CCU209247 | Z4: CCU209247 | AA4: Shipped - Pre-alert to be sent // Booked on 26.02.26 // Supplier response rcvd on 26.02.26 // As on 06.03.26 The vessel is delayed due to port congestion, and delays may increase due to the current situation in the Middle East // Carrier informed on 10.03.2026 that cargo has been booked on an earlier vessel // Carrier informed on 10.03.2026 that cargo has been booked on an earlier vessel ONE RECOMMENDATION // On 17.03.26, the carrier informed that the vessel ONE Recommendation is delayed due to adverse weather conditions on the import-bound leg. The revised ETA at Hamburg is now 22.03.26. | AB4: Non-stackable
A5: GERMANY CCU 2 | AA5: New closing : 18.03.26 // closing : 17.03.26 // closing : 12.03.26 // closing : 11.03.26 // closing : 09.03.26 // closing : 05.03.26 // SAC9828-HMM ROTTERDAM // delayed due to port congestions. | AB5: 91-0003-603-00 // 91-0003-603-01
A6: SMS CONCAST AG // PARTIAL SHIPMENT LOT- 3 | B6: TSL/55639/2200058575 | C6: FOB | D6: HAM | E6: CCU | F6: 2 | G6: 1039 | H6: 1.44 | I6: HMM ROTTERDAM V.018E | J6: 46064 | K6: 46094 | L6: =K6-J6 -> 30 | M6: - | N6: 46098 | O6: =IF(ISBLANK(N6)=TRUE,TODAY()-J6,N6-J6) -> 34 | P6: 46106 | Q6: 46097 | S6: =IF(ISBLANK(R6)=TRUE,TODAY()-J6,R6-J6) -> 41 | U6: 46160 | V6: Z26001850220 | W6: 22-0008-604-00 | X6: 22-0008-604-00 | Y6: CCU209234 | Z6: CCU209234 | AA6: Sailing awaited // Booking updated on 20.02.26 // Booked on 18.02.26 // Supplier response rcvd on 13.02.26 // On 19.02.26, the supplier requested to shift the vessel to a later closing date, preferably no earlier than the end of next week, as the shipment is currently in Switzerland and the T1 and EUR.1 certificates are still to be issued // Carrier informed on 19.02.26 that Vessel changed to ONE Innovation due to early arrival of HMM Copenhagen and earlier VGM deadline - New schedule: Closing 24.02, ETD 02.03 // On 20.02.26, the carrier informed that the vessel ONE Innovation is delayed due to port congestion // Supplier informed on 20.02.26 that they will issue the T1 at beginning of next week // On 20.02.26 carrier informed that vessel delayed due to port congestions // As on 06.03.26 The vessel is delayed due to port congestion, and delays may increase due to the current situation in the Middle East // Supplier confirmed on 10.03.26 that they will provide the MRN, and no T1 document will be issued for this shipment. MRN rcvd on 13.03.26 // On 16.03.26 carrier informed that vessel HMM Rotterdam is delayed due to port congestions. | AB6: Stackable
A7: PRIMETALS TECHNOLOGIES // COMPLETE SHIPMENT LOT- 1 | B7: TSL/56966/2200060906 | C7: FOB | D7: HAM | E7: CCU | F7: 1 | G7: 420 | H7: 1.651 | I7: HMM ROTTERDAM V.018E | J7: 46080 | K7: 46083 | L7: =K7-J7 -> 3 | M7: 46090 | N7: 46093 | O7: =IF(ISBLANK(N7)=TRUE,TODAY()-J7,N7-J7) -> 13 | P7: 46106 | Q7: 46097 | S7: =IF(ISBLANK(R7)=TRUE,TODAY()-J7,R7-J7) -> 25 | U7: 46160 | V7: Z26001494351 | W7: 22-0009-604-00 | X7: 22-0009-604-00 | Z7: CCU209257 | AA7: Sailing awaited // Booked on 03.03.26 // Supplier response & MRN rcvd on 02.03.26 // As on 06.03.26 The vessel is delayed due to port congestion, and delays may increase due to the current situation in the Middle East // On 12.03.26, it was mentioned in the CWR that 1 x packaging was damaged - Carrier taped the package on 17.03.26 // On 16.03.26 carrier informed that vessel HMM Rotterdam is delayed due to port congestions. | AB7: Stackable // Repairing charges would be EUR 180 billed to supplier
A8: ALPINE METAL // COMPLETE SHIPMENT LOT- 1 | B8: TSL/57653/2200061997 | C8: FOB | D8: HAM | E8: CCU | F8: 1 | G8: 1520 | H8: 1.424 | I8: HMM ROTTERDAM V.018E | J8: 46084 | K8: 46084 | L8: =K8-J8 -> 0 | M8: - | N8: 46092 | O8: =IF(ISBLANK(N8)=TRUE,TODAY()-J8,N8-J8) -> 8 | P8: 46106 | Q8: 46101 | S8: =IF(ISBLANK(R8)=TRUE,TODAY()-J8,R8-J8) -> 21 | U8: 46160 | V8: Z26001710968 | W8: 22-0010-604-00 | X8: 22-0010-604-00 | Z8: CCU209261 | AA8: Sailing awaited // Booked on 05.03.26 // Supplier response & MRN rcvd on 03.03.26 // As on 06.03.26 The vessel is delayed due to port congestion, and delays may increase due to the current situation in the Middle East // On 16.03.26 carrier informed that vessel HMM Rotterdam is delayed due to port congestions. | AB8: Stackable
A9: BUCK // Complete Shipment LOT :- 01 | B9: TSL/56554/2200060284 | C9: EXW | D9: HAM | E9: CCU | F9: 1 | G9: 959 | H9: 0.343 | I9: HMM ROTTERDAM V.018E | J9: 46084 | K9: 46087 | L9: =K9-J9 -> 3 | M9: 46087 | N9: 46093 | O9: =IF(ISBLANK(N9)=TRUE,TODAY()-J9,N9-J9) -> 9 | P9: 46106 | Q9: 46101 | S9: =IF(ISBLANK(R9)=TRUE,TODAY()-J9,R9-J9) -> 21 | U9: 46160 | V9: S26100029103 | W9: 22-0011-604-00 | X9: 22-0011-604-00 | Z9: CCU209262 | AA9: Sailing awaited // Booked on 05.03.26 // Supplier response rcvd on 03.03.26 // T1 rcvd on 06.03.26 // As on 06.03.26 The vessel is delayed due to port congestion, and delays may increase due to the current situation in the Middle East // On 12.03.26, it was mentioned 1 x SKIDS ARE DAMAGED in the CWR - Carrier taped the package on 18.03.26 // On 16.03.26 carrier informed that vessel HMM Rotterdam is delayed due to port congestions. | AB9: Non-stackable
A10: GERMANY CCU 3 | AA10: New closing : 24.03.26 // Closing : 23.03.26 // SAC9829 | AB10: 91-0001-604-00
A11: TMT // COMPLETE SHIPMENT LOT- 1 | B11: TSL/57339/2200061522 | C11: EXW | D11: HAM | E11: CCU | F11: 1 | G11: 850 | H11: 0.852 | I11: HMM ST PETERSBURG V.017E | J11: 46087 | K11: 46087 | L11: =K11-J11 -> 0 | M11: 46092 | N11: 46094 | O11: =IF(ISBLANK(N11)=TRUE,TODAY()-J11,N11-J11) -> 7 | P11: 46112 | Q11: 46111 | S11: =IF(ISBLANK(R11)=TRUE,TODAY()-J11,R11-J11) -> 18 | U11: 46162 | V11: Z26001711792 | W11: 22-0012-604-00 | X11: 22-0012-604-00 | Z11: CCU209265 | AA11: Booked on 06.03.26 // MRN available // Supplier response rcvd on 06.03.26 // Trucker informed on 11.03.26 that their partner unfortunately could not pick up the shipment yesterday. Therefore, the pickup has been rescheduled for 11.03.26 // On 16.03.26 carrier informed that vessel HMM Rotterdam is delayed due to port congestions. // The carrier on 18.03.26 informed that the shipment has been rolled over due to space constraints // The carrier has informed on 20.03.26 that the vessel HMM St. Petersburg is delayed due to port congestion. | AB11: Stackable
A12: CHINA CCU
A13: CHANGZHI // ST00002290 | B13: TSL/2200061760 | C13: FOB | D13: TJN | E13: CCU | F13: 1 | G13: 705 | H13: 0.705 | I13: TBA | J13: 46080 | K13: 46080 | L13: =K13-J13 -> 0 | M13: - | N13: 46094 | O13: =IF(ISBLANK(N13)=TRUE,TODAY()-J13,N13-J13) -> 14 | P13: 46106 | Q13: 46099 | S13: =IF(ISBLANK(R13)=TRUE,TODAY()-J13,R13-J13) -> 25 | U13: 46123 | V13: - | X13: SGE25260279 | AA13: Sailing awaited // Booked // Supplier response rcvd on 06.03.26 // TKM China team informed on 16.03.26 that since the shipper’s packing needs to be redone, the shipment is now booked for ETD 25.03.26
A14: BEIJING WIS WIZ // ST00002312 | B14: TSL/2200061732 | C14: FOB | D14: XIN | E14: CCU | F14: 2 | G14: 1030 | H14: 4.86 | I14: TBA | J14: 46085 | K14: 46098 | L14: =K14-J14 -> 13 | M14: - | O14: =IF(ISBLANK(N14)=TRUE,TODAY()-J14,N14-J14) -> 20 | S14: =IF(ISBLANK(R14)=TRUE,TODAY()-J14,R14-J14) -> 20 | V14: - | X14: SGE25260290 | Y14: GTJCOL26030193 | AA14: Booking confirmation awaited
A15: Metallon Holdings Limited // Exceeds contractual lot limit. | B15: TSL/57444/2200061614 | C15: EXW | D15: TJN | E15: CCU | F15: 1 | G15: 1416 | H15: =290*180*170/1000000 -> 8.874 | I15: TBA | J15: 46094 | K15: 46099 | L15: =K15-J15 -> 5 | M15: - | N15: 46102 | O15: =IF(ISBLANK(N15)=TRUE,TODAY()-J15,N15-J15) -> 8 | P15: 46113 | Q15: 46114 | S15: =IF(ISBLANK(R15)=TRUE,TODAY()-J15,R15-J15) -> 11 | U15: 46144 | V15: - | W15: 32-0001-604-00 | X15: SGE25260292 | Y15: GTJCOL26030241 | AA15: Booked on 18.03.26 // Cargo transit to TJN is approximately 5 days, targeting ETD 02 April // Revised docs with correct incoterm rcvd on 17.03.26 | AB15: overlength freight
A16: CHINA NSA
A17: CHANGZHOU ECCO ROLLER CO.,LTD // ST00002344 | B17: TSL/2200059445 | C17: TBA | D17: SHG | E17: NSA | F17: 2 | G17: 8400 | H17: 4.731 | J17: 46094 | L17: =K17-J17 -> -46094 | O17: =IF(ISBLANK(N17)=TRUE,TODAY()-J17,N17-J17) -> 11 | S17: =IF(ISBLANK(R17)=TRUE,TODAY()-J17,R17-J17) -> 11 | V17: - | AA17: Confirmation from Tata Steel on the quote is still awaited. | AB17: NS //
A18: ITALY CCU
A19: TECNO // Complete Shipment LOT :- 01 | B19: TSL/57374/2200061473 | C19: EXW | D19: GEN | E19: CCU | F19: 1 | G19: 1660 | H19: 1.755 | I19: ONE FRIENDSHIP / 011E | J19: 46084 | K19: 46084 | L19: =K19-J19 -> 0 | M19: 46090 | N19: 46091 | O19: =IF(ISBLANK(N19)=TRUE,TODAY()-J19,N19-J19) -> 7 | P19: 46102 | Q19: 46099 | S19: =IF(ISBLANK(R19)=TRUE,TODAY()-J19,R19-J19) -> 21 | U19: 46150 | V19: - | W19: 22-0014-604-00 | X19: 22-0015-603-00 | Y19: MILCCU6232051V | Z19: MILCCU6232051V | AA19: Sailing confirmation awaited // In tracking showing ETD 23.03.26 // Booked on 04.03.26 // Closing :12.03.26 // MRN by us // This is the first available vessel // Delay - due to strong congestion at port and delay to previous shipment | AB19: NS // WD2603107080 // Rev MBL correct // MRN rec on 12.03.26
A20: PICCARDI S.r.L // Complete Shipment LOT :- 01 | B20: TSL/57462/2200061588 | C20: FOB | D20: GEN | E20: CCU | F20: 1 | G20: 358.3 | H20: 0.482 | I20: ONE FRIENDSHIP / 011E | J20: 46084 | K20: 46084 | L20: =K20-J20 -> 0 | M20: 46090 | N20: 46090 | O20: =IF(ISBLANK(N20)=TRUE,TODAY()-J20,N20-J20) -> 6 | P20: 46102 | Q20: 46099 | S20: =IF(ISBLANK(R20)=TRUE,TODAY()-J20,R20-J20) -> 21 | U20: 46150 | V20: - | W20: 23-0001-604-00 | X20: 23-0003-603-00 | Y20: MILCCU6232118V | Z20: MILCCU6232118V | AA20: Sailing confirmation awaited // In tracking showing ETD 23.03.26 // Booked on 04.03.26 // Closing :12.03.26 // MRN rcvd on 11.03.26 // This is the first available vessel// Delay - due to strong congestion at port and delay to previous shipment | AB20: NS // WD2603107274 // Draft MBL correct // MRN REC ON 11.03
A21: ITALY NSA
A22: UK
A23: COREWIRE LIMITED | B23: TSL/57671/4416366332 | C23: EXW | D23: LON | E23: CCU | F23: 8 | G23: 6340 | H23: 8.358 | I23: MAERSK MC-KINNEY MOLLER / 611E | J23: 46086 | K23: 46086 | L23: =K23-J23 -> 0 | M23: 46090 | N23: 46091 | O23: =IF(ISBLANK(N23)=TRUE,TODAY()-J23,N23-J23) -> 5 | P23: 46101 | Q23: 46101 | S23: =IF(ISBLANK(R23)=TRUE,TODAY()-J23,R23-J23) -> 19 | U23: 46133 | V23: - | W23: 22-0004-604-00 | X23: UINCCU021867 | Y23: UINCCU021895 | Z23: SUSE26021867 | AA23: Sailing awaited // Booked on 06.03.26 // Closing : 16.03.26 // This is the first available vessel. | AB23: Non Stackable // HBL correct // Draft MBL rcvd on 16.03.25
A24: CANADA
A25: METAL 7 // COMPLETE SHIPMENT LOT- 1 | B25: TSL/57472/2200061692 | C25: EXW | D25: HAL | E25: CCU | F25: 4 | G25: 3334 | H25: 3.92 | I25: HMM SAPPHIRE / 010W | J25: 46091 | K25: 46091 | L25: =K25-J25 -> 0 | M25: 46094 | N25: 46097 | O25: =IF(ISBLANK(N25)=TRUE,TODAY()-J25,N25-J25) -> 6 | P25: 46115 | Q25: 46115 | S25: =IF(ISBLANK(R25)=TRUE,TODAY()-J25,R25-J25) -> 14 | U25: 46145 | V25: - | W25: 22-0005-604-00 | Z25: MTRCCU6103984V | AA25: Sailing awaited // Booked on 11.03.26 // closing : 27.03.26 // Supplier response rcvd 10.03.26 that they need flatbed truck // This is the first available vessel. | AB25: Stackable // Draft HBL/MBL awaited
A26: USA
A27: Mi-Jack Products Inc. | B27: TSL/57595/2200061922 | C27: EXW | D27: LAX | E27: CCU | F27: 2 | G27: 576.0623 | H27: 1.117 | I27: ONE HARBOUR V.103W | J27: 46093 | K27: 46093 | L27: =K27-J27 -> 0 | M27: 46098 | N27: 46099 | O27: =IF(ISBLANK(N27)=TRUE,TODAY()-J27,N27-J27) -> 6 | P27: 46118 | Q27: 46118 | S27: =IF(ISBLANK(R27)=TRUE,TODAY()-J27,R27-J27) -> 12 | U27: 46153 | V27: - | W27: 22-0013-604-00 | X27: ORDSE0247080 | Y27: CHI/CTA/V03422 | Z27: CHI/CTA/V03422 | AA27: Sailing awaited // Booked 17.03.26 // closing : 18.03.26 // Supplier response rcvd on 12.03.26 // This is the first available vessel. | AB27: Non-stackable // Draft HBL/MBL 20.03.26
A28: NON-TATA
A29: Intensiv Filter | B29: SOC-04579 | C29: CIF | D29: HAM | E29: JED | F29: 3 | G29: 695 | H29: 5.357 | I29: SAVANNAH EXPRESS | J29: 46044 | L29: =K29-J29 -> -46044 | O29: =IF(ISBLANK(N29)=TRUE,TODAY()-J29,N29-J29) -> 61 | P29: 46063 | Q29: 46110 | R29: 46071 | S29: =IF(ISBLANK(R29)=TRUE,TODAY()-J29,R29-J29) -> 27 | T29: 46072 | V29: Z26000667113 | W29: 28-0008-602-00 | X29: 28-0008-602-00 | Z29: SEME26020002704 | AA29: Pick-up details awaited // booking confirmation received
A30: Impact - Maxxove | B30: 2025-40038 | C30: CFR | D30: HAM | E30: JEA | F30: 3 | G30: 2247 | H30: 3.074 | I30: SAVANNAH EXPRESS | J30: 46050 | L30: =K30-J30 -> -46050 | M30: 46052 | N30: 46055 | O30: =IF(ISBLANK(N30)=TRUE,TODAY()-J30,N30-J30) -> 5 | P30: 46066 | Q30: 46099 | R30: 46071 | S30: =IF(ISBLANK(R30)=TRUE,TODAY()-J30,R30-J30) -> 21 | T30: 46072 | V30: Z26000673872 | W30: 28-0009-602-00 | X30: 28-0009-602-00 | Z30: SEME26020002708 | AA30: goods has been delivered to the warehouse /
A31: Intensiv Filter | B31: SOC-04348 // MM-010-10-25 | C31: CIF | D31: HAM | E31: EDK | F31: 4 | G31: 1015 | H31: 4.138 | I31: EXPRESS SPAIN | J31: 46051 | K31: 46051 | L31: =K31-J31 -> 0 | M31: 46051 | N31: 46070 | O31: =IF(ISBLANK(N31)=TRUE,TODAY()-J31,N31-J31) -> 19 | P31: 28.03.2026 | S31: =IF(ISBLANK(R31)=TRUE,TODAY()-J31,R31-J31) -> 54 | U31: 15.04.2026 | V31: Z26001435390 | W31: 25-0011-603-00 | X31: 25-0011-603-00 | Z31: EDK217768 / 1088027 | AA31: ACID number received on 16.02.2026 // physical inspection needed / customs have been contacted / waiting for the release
A32: John Zink - Balmer Lawrie | B32: 4070059507 | C32: FOB | D32: ANT | E32: NSA | F32: 1 | G32: 345 | H32: 2.19 | I32: MV One Reliability | J32: 46064 | K32: 46070 | L32: =K32-J32 -> 6 | M32: 46072 | O32: =IF(ISBLANK(N32)=TRUE,TODAY()-J32,N32-J32) -> 41 | P32: 09.03.2026 | Q32: 02.03.2026 | R32: 46090 | S32: =IF(ISBLANK(R32)=TRUE,TODAY()-J32,R32-J32) -> 26 | T32: 46101 | U32: 08.04.2026 | V32: - | W32: 25-0013-603-00 | X32: 25-0013-603-00 | Y32: B2601714 | Z32: B2601714 | AA32: received MBL
A33: WEG Gear Systems GmbH - Balmer Lawrie | B33: RITM11181450 // 4130002885 | C33: EXW | D33: HAM | E33: NSA | F33: 2 | G33: 2024 | H33: 6.134 | I33: ONE RECOMMENDATION | J33: 02.03.2026 | K33: 02.03.2026 | L33: =K33-J33 -> #VALUE! | M33: 05.03.2026 | O33: =IF(ISBLANK(N33)=TRUE,TODAY()-J33,N33-J33) -> #VALUE! | P33: 22.03.2026 | V33: Z26001669900 | W33: 25-0027-603-00 | X33: 25-0027-603-00 | Z33: 50-0326-5093-13 | AA33: SSS , HBL confirmed, MBL received
A34: J A Becker& Söhne - Balmer Lawrie | B34: 4130002910 | C34: EXW | D34: HAM | E34: NSA | F34: 1 | G34: 775 | H34: 4.139 | I34: ONE RECOMMENDATION | J34: 23.02.2026 | K34: 46080 | L34: =K34-J34 -> #VALUE! | M34: 02.03.2026 | N34: 10.03.2026 | O34: =IF(ISBLANK(N34)=TRUE,TODAY()-J34,N34-J34) -> #VALUE! | P34: 22.03.2026 | V34: Z26001609058 | W34: 25-0023-603-00 | X34: 25-0023-603-00 | Z34: 50-0326-5093-09 | AA34: seven seas, MBL received, HBL confirmed
A35: Impact - Maxxove | B35: 2025-40068 IISCO | C35: CFR | D35: HAM | E35: NSA | F35: 3 | G35: 2999 | H35: 3.716 | I35: ONE RECOMMENDATION | J35: 03.03.2026 | K35: 03.03.2026 | L35: =K35-J35 -> #VALUE! | M35: 04.03.2026 | O35: =IF(ISBLANK(N35)=TRUE,TODAY()-J35,N35-J35) -> #VALUE! | P35: 22.03.2026 | Q35: 46099 | U35: 10.05.2026 | V35: Z26001598076 | W35: 25-0024-603-00 | X35: 25-0024-603-00 | Z35: SEIN26030010212 | AA35: WOAC, original BL // awaiting final BL / HBL confirmed + certificate confirmed
A36: MALMEDIE - Balmer Lawrie | B36: 4130002913, uns. Ref. AB25624 | C36: FOB | D36: HAM | E36: NSA | F36: 1 | G36: 1585 | H36: 1.378 | I36: BF HAMBURG | J36: 09.03.2026 | K36: 05.03.2026 | L36: =K36-J36 -> #VALUE! | P36: 26.03.2026 | Q36: 46104 | V36: Z26001847975 | W36: 25-0001-604-00 | X36: 25-0001-604-00 | Z36: 50-0326-5099-08 | AA36: seven seas // rec. MBL draft is okay // HBL draft confirmation awaited
A37: John Zink - Balmer Lawrie | B37: GAIL/PA25/30812/5100004373 | C37: FOB | D37: ANT | E37: NSA | F37: 1 | G37: 259 | H37: 0.61 | I37: BF HAMBURG | J37: 04.03.2026 | K37: 04.03.2026 | L37: =K37-J37 -> #VALUE! | M37: 46097 | N37: 46099 | O37: =N37-M37 -> 2 | P37: 25.03.2026 | U37: 28.04.2026 | V37: - | W37: 25-0004-604-00 | X37: 25-0004-604-00 | Z37: B2602743 | AA37: NS, Cleve // HBL and MBL draft confirmation awaited
A38: Impact - Maxxove | B38: 2026-40002 | C38: CIF | D38: HAM | E38: MAA | F38: 4 | G38: 3626 | H38: 4643 | I38: MAERSK SAVANNAH | J38: 46087 | K38: 46090 | L38: =K38-J38 -> 3 | M38: 46093 | P38: 46111 | U38: 46144 | Z38: SEIN26030011709 | AA38: WOAC
A39: Impact - Maxxove | B39: 2025-40032 | Fourth partial delivery | C39: CIF | D39: HAM | E39: MAA | F39: 2 | G39: 2428 | H39: 3471 | I39: MAERSK SEOUL | J39: 46097 | K39: 46097 | L39: =K39-J39 -> 0 | M39: 46104 | P39: 46117 | U39: 46151 | Z39: SEIN26040015207 | AA39: WOAC
A40: PROFINE | B40: Tour 1010699377 | C40: CIF | D40: HAM | E40: NAS | F40: 3 | G40: 2652 | J40: 46069 | K40: 46097 | L40: =K40-J40 -> 28 | O40: =IF(ISBLANK(N40)=TRUE,TODAY()-J40,N40-J40) -> 36 | U40: 30.04.2026 | AA40: Readiness of the goods from KW12 // DG GOODS / SACO: offer Nr. 290047 // CIPL will be provided the day before pick-up
A41: Paul Wurth - Balmer Lawrie | B41: 4130002916 | C41: FOB | D41: HAM /ANT | E41: NSA | F41: 1 | G41: 652
A42: Refra (K&N 256623) | B42: 4300041281 | C42: FOB | D42: ANT | E42: BUE | F42: 9 | G42: 8355 | H42: 8712 | J42: 46104 | AA42: FOB Delivery only, shipping by K&N

Sheet LCL Completed
A1: Supplier | B1: PO number | C1: Incoterm | D1: POL | E1: POD | F1: No. of Pieces | G1: Gross Wt. (Kgs) | H1: CBM | I1: Vessel | J1: Release date | K1: Readiness | L1: Days Count (Release Dt. - Readiness Dt.) | M1: Pickup | N1: Arrival at Warehouse | O1: Days Count (Release Dt. - Arrival at WH Dt.) | P1: ETD | Q1: Intended ETD | R1: Shipped on Board | S1: Days Count (Release Dt. - SOB Dt.) | T1: Pre-alert Date | U1: Z NO. // ETA | V1: Z No. | W1: Position No. | X1: HBL | Y1: MBL | Z1: Booking No. | AA1: Remarks | AB1: Additional Remarks | AC1: Pre-alert Remarks | AD1: Pre-Alert saved | AE1: Final commercial docs. Status | AF1: Error in release mail
A2: Maina | B2: TSL/48838/2299900795 | C2: FOB | D2: GEN | E2: CCU | F2: 2 pcs | G2: 5480 | H2: 6.66 | I2: Al Riffa | J2: 44630 | K2: 44634 | M2: 44635 | N2: 44637 | O2: =IF(ISBLANK(N2)=TRUE,TODAY()-J2,N2-J2) -> 7 | P2: 44664 | Q2: 44644 | R2: 44664 | S2: =IF(ISBLANK(R2)=TRUE,TODAY()-J2,R2-J2) -> 34 | T2: 44670 | X2: 23-0001-204 | AA2: rebooked by Carrier ex Alula Express / etd 24.03.2022
A3: Tecno Vibrazioni | B3: TSL/47735/22000047068 | C3: EXW | D3: GEN | E3: CCU | F3: 1 pcs | G3: 350 | H3: 1.33 | I3: Al Riffa | J3: 44631 | K3: 44635 | M3: 44636 | N3: 44638 | O3: =IF(ISBLANK(N3)=TRUE,TODAY()-J3,N3-J3) -> 7 | P3: 44664 | Q3: 44644 | R3: 44664 | S3: =IF(ISBLANK(R3)=TRUE,TODAY()-J3,R3-J3) -> 33 | T3: 44670 | X3: 22-0005-204 | AA3: stopped by TLL, released on 15.03.2022 // rebooked by Carrier ex Alula Express / etd 24.03.2022
A4: Thermocast | B4: TSL/48915/2200048530 | C4: FOB | D4: GEN | E4: CCU | F4: 1 pcs | G4: 1620 | H4: 2.09 | I4: Al Riffa | J4: 44634 | K4: 44635 | M4: 44636 | N4: 44638 | O4: =IF(ISBLANK(N4)=TRUE,TODAY()-J4,N4-J4) -> 4 | P4: 44664 | Q4: 44644 | R4: 44664 | S4: =IF(ISBLANK(R4)=TRUE,TODAY()-J4,R4-J4) -> 30 | T4: 44670 | X4: 22-0007-204 | AA4: rebooked by Carrier ex Alula Express / etd 24.03.2022
A5: Tenova | B5: TSL/48487/2200048172 | C5: FOB | D5: GEN | E5: CCU | F5: 1 pcs | G5: 675 | H5: 3.381 | I5: Al Riffa | J5: 44634 | K5: 44638 | N5: 44642 | O5: =IF(ISBLANK(N5)=TRUE,TODAY()-J5,N5-J5) -> 8 | P5: 44664 | Q5: 44644 | R5: 44664 | S5: =IF(ISBLANK(R5)=TRUE,TODAY()-J5,R5-J5) -> 30 | T5: 44670 | X5: 22-0006-204 | AA5: rebooked by Carrier ex Alula Express / etd 24.03.2022
A6: Thermocast | B6: TSL/48969/2200048665 | C6: FOB | D6: GEN | E6: CCU | F6: 2 pcs | G6: 3480 | H6: 4.95 | I6: Al Riffa | J6: 44644 | K6: 44644 | M6: 44648 | N6: 44650 | O6: =IF(ISBLANK(N6)=TRUE,TODAY()-J6,N6-J6) -> 6 | P6: 44664 | Q6: 44664 | R6: 44664 | S6: =IF(ISBLANK(R6)=TRUE,TODAY()-J6,R6-J6) -> 20 | T6: 44670 | X6: 22-0009-204 | AA6: vessel delayed Al Riffa / etd 31.03.2022
A7: Refra Technik | B7: 4300026803 | C7: CFR | D7: HAM | E7: MNL | F7: 1 pcs | G7: 223kgs | H7: 0.995 | I7: CMA CGM Zheng He | J7: 44638 | K7: 44638 | M7: 44648 | N7: 44649 | O7: =IF(ISBLANK(N7)=TRUE,TODAY()-J7,N7-J7) -> 11 | Q7: 44665 | R7: 44665 | S7: =IF(ISBLANK(R7)=TRUE,TODAY()-J7,R7-J7) -> 27 | T7: 44665 | X7: 25-0006-204 | AA7: Rebooked by Carrier from Ever Gifted / etd 07.04.2022
A8: Reel | C8: CFR | D8: HAM | E8: SHA | F8: 1 pcs | G8: 360 | H8: 0.672 | I8: CP Universe | J8: 44645 | K8: 44648 | M8: 44651 | N8: 44656 | O8: =IF(ISBLANK(N8)=TRUE,TODAY()-J8,N8-J8) -> 11 | Q8: 44664 | R8: 44669 | S8: =IF(ISBLANK(R8)=TRUE,TODAY()-J8,R8-J8) -> 24 | T8: 44673 | X8: 25-0008-204
A9: BSA | B9: TSL/48330/2200047730 | C9: FOB | D9: GEN | E9: CCU | F9: 2 pcs | G9: 2886 | H9: 3.36 | I9: Milano Bridge | J9: 44616 | K9: 44650 | M9: 44650 | N9: 44651 | O9: =IF(ISBLANK(N9)=TRUE,TODAY()-J9,N9-J9) -> 35 | P9: 44669 | Q9: 44666 | R9: 44669 | S9: =IF(ISBLANK(R9)=TRUE,TODAY()-J9,R9-J9) -> 53 | T9: 44672 | X9: 22-0004-204 | AA9: vessel delayed Milano Bridge / etd 15.04.2022
A10: Tecno Vibrazioni | B10: TSL/49093/2200048866 | C10: EXW | D10: GEN | E10: CCU | F10: 1 pcs | G10: 260 | H10: 0.576 | I10: Milano Bridge | J10: 44650 | K10: 44652 | M10: 44655 | N10: 44657 | O10: =IF(ISBLANK(N10)=TRUE,TODAY()-J10,N10-J10) -> 7 | P10: 44669 | Q10: 44666 | R10: 44669 | S10: =IF(ISBLANK(R10)=TRUE,TODAY()-J10,R10-J10) -> 19 | T10: 44672 | X10: 22-0026-204 | AA10: vessel delayed Milano Bridge / etd 15.04.2022
A11: Impact / Jiangsu | C11: CFR | D11: HAM | E11: NSA | F11: 3 pcs | G11: 2003 | H11: 2.874 | I11: Northern Justice | J11: 44650 | K11: 44651 | M11: 44651 | N11: 44656 | O11: =IF(ISBLANK(N11)=TRUE,TODAY()-J11,N11-J11) -> 6 | Q11: 44662 | R11: 44674 | S11: =IF(ISBLANK(R11)=TRUE,TODAY()-J11,R11-J11) -> 24 | T11: 44676 | X11: 25-0007-204
A12: PWL | B12: TSL/49050/2200048660 | C12: FOB | D12: HAM | E12: CCU | F12: 1 pcs | G12: 255 | H12: 1.764 | I12: Northern Justice | J12: 44643 | K12: 44610 | N12: 44648 | O12: =IF(ISBLANK(N12)=TRUE,TODAY()-J12,N12-J12) -> 5 | P12: 44674 | Q12: 44622 | R12: 44674 | S12: =IF(ISBLANK(R12)=TRUE,TODAY()-J12,R12-J12) -> 31 | T12: 44679 | X12: 22-0031-204 | AA12: rebooked by Carrier ex MSC Aliya / ETD 02.03.2022
A13: Binder | B13: TSL/48696/2200047482 | C13: EXW | D13: HAM | E13: CCU | F13: 6 pcs | G13: 9345 | H13: 35.774 | I13: Northern Justice | J13: 44608 | K13: 44609 | M13: 44613 | N13: 44620 | O13: =IF(ISBLANK(N13)=TRUE,TODAY()-J13,N13-J13) -> 12 | P13: 44674 | Q13: 44622 | R13: 44674 | S13: =IF(ISBLANK(R13)=TRUE,TODAY()-J13,R13-J13) -> 66 | T13: 44679 | X13: 22-0018-203 | AA13: rebooked by Carrier ex MSC Aliya / ETD 02.03.2022
A14: Malmedie | B14: TSL/49150/3700847821 | C14: FOB | D14: HAM | E14: CCU | F14: 1 pcs | G14: 1550 | H14: 1.14 | I14: Northern Justice | J14: 44614 | K14: 44615 | N14: 44617 | O14: =IF(ISBLANK(N14)=TRUE,TODAY()-J14,N14-J14) -> 3 | P14: 44674 | Q14: 44622 | R14: 44674 | S14: =IF(ISBLANK(R14)=TRUE,TODAY()-J14,R14-J14) -> 60 | T14: 44679 | X14: 22-0020-203 | AA14: rebooked by Carrier ex MSC Aliya / ETD 02.03.2022
A15: Malmedie | B15: TSL/49151/3700845190 | C15: FOB | D15: HAM | E15: CCU | F15: 1 pcs | G15: 518 | H15: 0.573 | I15: Northern Justice | J15: 44613 | K15: 44615 | N15: 44617 | O15: =IF(ISBLANK(N15)=TRUE,TODAY()-J15,N15-J15) -> 4 | P15: 44674 | Q15: 44622 | R15: 44674 | S15: =IF(ISBLANK(R15)=TRUE,TODAY()-J15,R15-J15) -> 61 | T15: 44679 | X15: 22-0023-203 | AA15: rebooked by Carrier ex MSC Aliya / ETD 02.03.2022
A16: Eich | B16: TSL/48301/2200047899 | C16: EXW | D16: HAM | E16: CCU | F16: 1 pcs | G16: 784 | H16: 0.843 | I16: Northern Justice | J16: 44637 | K16: 44642 | M16: 44644 | N16: 44649 | O16: =IF(ISBLANK(N16)=TRUE,TODAY()-J16,N16-J16) -> 12 | P16: 44674 | Q16: 44665 | R16: 44674 | S16: =IF(ISBLANK(R16)=TRUE,TODAY()-J16,R16-J16) -> 37 | T16: 44679 | X16: 22-0028-204 | AA16: rebooked by Carrier ex Seamax Fairfield / etd 14.04.2022
A17: Eich | B17: TSL/48335/3700839504 | C17: EXW | D17: HAM | E17: CCU | F17: 2 pcs | G17: 1536 | H17: 1.226 | I17: Northern Justice | J17: 44638 | K17: 44642 | M17: 44644 | N17: 44649 | O17: =IF(ISBLANK(N17)=TRUE,TODAY()-J17,N17-J17) -> 11 | P17: 44674 | Q17: 44665 | R17: 44674 | S17: =IF(ISBLANK(R17)=TRUE,TODAY()-J17,R17-J17) -> 36 | T17: 44679 | X17: 22-0029-204 | AA17: rebooked by Carrier ex Seamax Fairfield / etd 14.04.2022
A18: Eich | B18: TSL/48433/4407993146 | C18: EXW | D18: HAM | E18: CCU | F18: 1 pcs | G18: 362 | H18: 0.226 | I18: Northern Justice | J18: 44648 | K18: 44650 | M18: 44651 | N18: 44656 | O18: =IF(ISBLANK(N18)=TRUE,TODAY()-J18,N18-J18) -> 8 | P18: 44674 | Q18: 44665 | R18: 44674 | S18: =IF(ISBLANK(R18)=TRUE,TODAY()-J18,R18-J18) -> 26 | T18: 44679 | X18: 22-0030-204 | AA18: rebooked by Carrier ex Seamax Fairfield / etd 14.04.2022
A19: PWL | B19: TSL/49050/2200048660 | C19: FOB | D19: HAM | E19: CCU | F19: 1 pcs | G19: 255 | H19: 1.232 | I19: Northern Justice | J19: 44643 | K19: 44649 | N19: 44657 | O19: =IF(ISBLANK(N19)=TRUE,TODAY()-J19,N19-J19) -> 14 | P19: 44674 | Q19: 44665 | R19: 44674 | S19: =IF(ISBLANK(R19)=TRUE,TODAY()-J19,R19-J19) -> 31 | T19: 44679 | X19: 22-0031-204 | AA19: rebooked by Carrier ex Seamax Fairfield / etd 14.04.2022
A20: PWL | B20: TSL/47933/2200047402 | C20: FOB | D20: HAM | E20: CCU | F20: 3 pcs | G20: 4080 | H20: 19.618 | I20: Northern Justice | J20: 44643 | K20: 44651 | N20: 44659 | O20: =IF(ISBLANK(N20)=TRUE,TODAY()-J20,N20-J20) -> 16 | P20: 44674 | Q20: 44665 | R20: 44674 | S20: =IF(ISBLANK(R20)=TRUE,TODAY()-J20,R20-J20) -> 31 | T20: 44679 | X20: 22-0032-204 | AA20: rebooked by Carrier ex Seamax Fairfield / etd 14.04.2022
A21: SIJ Ravne | B21: TSL/49077/2200048712 | C21: EXW | D21: HAM | E21: CCU | F21: 2 pcs | G21: 372 | H21: 0.14 | I21: Northern Justice | J21: 44650 | K21: 44652 | M21: 44656 | N21: 44659 | O21: =IF(ISBLANK(N21)=TRUE,TODAY()-J21,N21-J21) -> 9 | P21: 44674 | Q21: 44665 | R21: 44674 | S21: =IF(ISBLANK(R21)=TRUE,TODAY()-J21,R21-J21) -> 24 | T21: 44679 | X21: 22-0033-204 | AA21: rebooked by Carrier ex Seamax Fairfield / etd 14.04.2022
A22: Sibre | B22: TSL/48764/3700843744 | C22: FOB | D22: HAM | E22: CCU | F22: 2 pcs | G22: 712 | H22: 1.966 | I22: Northern Justice | J22: 44657 | K22: 44658 | M22: 44659 | N22: 44662 | O22: =IF(ISBLANK(N22)=TRUE,TODAY()-J22,N22-J22) -> 5 | P22: 44674 | Q22: 44665 | R22: 44674 | S22: =IF(ISBLANK(R22)=TRUE,TODAY()-J22,R22-J22) -> 17 | T22: 44679 | X22: 22-0034-204 | AA22: rebooked by Carrier ex Seamax Fairfield / etd 14.04.2022
A23: Sibre | B23: TSL/49260/3700850109 | C23: FOB | D23: HAM | E23: CCU | F23: 4 pcs | G23: 1227 | H23: 3.362 | I23: Northern Justice | J23: 44657 | K23: 44658 | M23: 44659 | N23: 44662 | O23: =IF(ISBLANK(N23)=TRUE,TODAY()-J23,N23-J23) -> 5 | P23: 44674 | Q23: 44665 | R23: 44674 | S23: =IF(ISBLANK(R23)=TRUE,TODAY()-J23,R23-J23) -> 17 | T23: 44679 | X23: 22-0035-204 | AA23: rebooked by Carrier ex Seamax Fairfield / etd 14.04.2022
A24: Atlantic | B24: TBD/2212/2200049018 | C24: FOB | D24: HAM | E24: CCU | F24: 5 pcs | G24: 1354 | H24: 2.555 | I24: Northern Justice | J24: 44656 | K24: 44656 | M24: 44659 | N24: 44663 | O24: =IF(ISBLANK(N24)=TRUE,TODAY()-J24,N24-J24) -> 7 | P24: 44674 | Q24: 44665 | R24: 44674 | S24: =IF(ISBLANK(R24)=TRUE,TODAY()-J24,R24-J24) -> 18 | T24: 44679 | X24: 22-0036-204-00 | AA24: rebooked by Carrier ex Seamax Fairfield / etd 14.04.2022
A25: Cavex | B25: TSL/48719/2200048435 | C25: FOB | D25: HAM | E25: CCU | F25: 1 pcs | G25: 378 | H25: 0.892 | I25: Northern Justice | J25: 44656 | K25: 44658 | M25: 44659 | N25: 44663 | O25: =IF(ISBLANK(N25)=TRUE,TODAY()-J25,N25-J25) -> 7 | P25: 44674 | Q25: 44665 | R25: 44674 | S25: =IF(ISBLANK(R25)=TRUE,TODAY()-J25,R25-J25) -> 18 | T25: 44679 | X25: 22-0037-204 | AA25: rebooked by Carrier ex Seamax Fairfield / etd 14.04.2022
A26: Metso | B26: TSL/48600/2200048120 | C26: EXW | D26: HAM | E26: CCU | F26: 1 pcs | G26: 1056 | H26: 1.386 | I26: Northern Justice | J26: 44650 | K26: 44652 | M26: 44655 | N26: 44662 | O26: =IF(ISBLANK(N26)=TRUE,TODAY()-J26,N26-J26) -> 12 | P26: 44674 | Q26: 44665 | R26: 44674 | S26: =IF(ISBLANK(R26)=TRUE,TODAY()-J26,R26-J26) -> 24 | T26: 44679 | X26: 22-0038-204 | AA26: rebooked by Carrier ex Seamax Fairfield / etd 14.04.2022
A27: Malmedie | B27: TSL/49398/3700851022 | C27: FOB | D27: HAM | E27: CCU | F27: 1 pcs | G27: 730 | H27: 0.632 | I27: Northern Justice | J27: 44659 | K27: 44662 | N27: 44664 | O27: =IF(ISBLANK(N27)=TRUE,TODAY()-J27,N27-J27) -> 5 | P27: 44674 | Q27: 44671 | R27: 44674 | S27: =IF(ISBLANK(R27)=TRUE,TODAY()-J27,R27-J27) -> 15 | T27: 44679 | X27: 22-0039-204 | AA27: vessel delayed
A28: Binder | B28: TSL/49633/2200049723 | C28: EXW | D28: HAM | E28: CCU | F28: 2 pcs | G28: 266 | H28: 1.747 | I28: Northern Justice | J28: 44657 | K28: 44658 | M28: 44662 | N28: 44665 | O28: =IF(ISBLANK(N28)=TRUE,TODAY()-J28,N28-J28) -> 8 | P28: 44674 | Q28: 44671 | R28: 44674 | S28: =IF(ISBLANK(R28)=TRUE,TODAY()-J28,R28-J28) -> 17 | T28: 44679 | X28: 22-0040-204 | AA28: vessel delayed
A29: Sarclad | B29: TICRC/1570/2200049378 | C29: EXW | D29: LON | E29: NSA | F29: 1 pcs | G29: 836 | H29: 2.278 | I29: MSC Azov | J29: 44637 | K29: 44641 | M29: 44641 | N29: 44644 | O29: =IF(ISBLANK(N29)=TRUE,TODAY()-J29,N29-J29) -> 7 | P29: 44669 | Q29: 44655 | R29: 44669 | S29: =IF(ISBLANK(R29)=TRUE,TODAY()-J29,R29-J29) -> 32 | T29: 44680 | AA29: vessel delayed
A30: Fosbel | B30: TSL/2200048968 | C30: FOB | D30: NYC | E30: CCU | F30: 3 pcs | G30: 3205 | H30: 3.398 | I30: YM Width | J30: 44615 | K30: 44615 | N30: 44624 | O30: =IF(ISBLANK(N30)=TRUE,TODAY()-J30,N30-J30) -> 9 | P30: 44655 | Q30: 44630 | R30: 44655 | S30: =IF(ISBLANK(R30)=TRUE,TODAY()-J30,R30-J30) -> 40 | T30: 44671 | X30: 22-0042-204 | AA30: vessel delayed by carrier / delay on paperwork by supplier
A31: Irizar | B31: TSL/48578/2200048263 | C31: FOB | D31: BIO | E31: CCU | F31: 1 pcs | G31: 341 | H31: 0.516 | I31: Al Nasriyah | J31: 44634 | K31: 44641 | N31: 44665 | O31: =IF(ISBLANK(N31)=TRUE,TODAY()-J31,N31-J31) -> 31 | P31: 44691 | Q31: 44657 | R31: 44661 | S31: =IF(ISBLANK(R31)=TRUE,TODAY()-J31,R31-J31) -> 27 | X31: 22-0001-205 | AA31: Supplier missed the closing on 26.03.2022 // Vsl delayed
A32: Irizar | B32: TSL/45072/2200043417 | C32: FOB | D32: BIO | E32: CCU | F32: 1 pcs | G32: 683 | H32: 0.637 | I32: Al Nasriyah | J32: 44637 | K32: 44641 | N32: 44665 | O32: =IF(ISBLANK(N32)=TRUE,TODAY()-J32,N32-J32) -> 28 | P32: 44691 | Q32: 44657 | R32: 44661 | S32: =IF(ISBLANK(R32)=TRUE,TODAY()-J32,R32-J32) -> 24 | X32: 22-0002-205 | AA32: Supplier missed the closing on 26.03.2022 // Vsl delayed
A33: Irizar | B33: TSL/47442/2200045643 | C33: FOB | D33: BIO | E33: CCU | F33: 1 pcs | G33: 680 | H33: 0.714 | I33: Al Nasriyah | J33: 44664 | K33: 44641 | N33: 44678 | O33: =IF(ISBLANK(N33)=TRUE,TODAY()-J33,N33-J33) -> 14 | P33: 44691 | Q33: 44679 | R33: 44661 | S33: =IF(ISBLANK(R33)=TRUE,TODAY()-J33,R33-J33) -> -3 | X33: 22-0003-205 | AA33: Vessel delayed
A34: Irizar | B34: TSL/48876/2200048476 | C34: FOB | D34: BIO | E34: CCU | F34: 2 pcs | G34: 1485 | H34: 1.855 | I34: Al Nasriyah | J34: 44671 | K34: 44672 | N34: 44679 | O34: =IF(ISBLANK(N34)=TRUE,TODAY()-J34,N34-J34) -> 8 | P34: 44691 | Q34: 44685 | R34: 44661 | S34: =IF(ISBLANK(R34)=TRUE,TODAY()-J34,R34-J34) -> -10 | X34: 22-0004-205 | AA34: Vessel Delayed
A35: Metal 7 | B35: TSL/48684/2200048372 | C35: FCA | D35: MTR | E35: CCU | F35: 1 pcs | G35: 335.6 | H35: 0.59 | I35: YM Truth | J35: 44599 | K35: 44630 | M35: 44630 | N35: 44644 | O35: =IF(ISBLANK(N35)=TRUE,TODAY()-J35,N35-J35) -> 45 | P35: 44675 | Q35: 44650 | R35: 44675 | S35: =IF(ISBLANK(R35)=TRUE,TODAY()-J35,R35-J35) -> 76 | AA35: Vessel Delayed at origin
A36: Metal 7 | B36: TSL/48683/22000483721 | C36: FCA | D36: MTR | E36: CCU | F36: 5 pcs | G36: 5075 | H36: 7.95 | I36: YM Truth | J36: 44628 | K36: 44630 | M36: 44630 | N36: 44644 | O36: =IF(ISBLANK(N36)=TRUE,TODAY()-J36,N36-J36) -> 16 | P36: 44675 | Q36: 44650 | R36: 44675 | S36: =IF(ISBLANK(R36)=TRUE,TODAY()-J36,R36-J36) -> 47 | AA36: Vessel Delayed at origin
A37: Metal 7 | B37: TSL/48686/2200048365 | C37: FCA | D37: MTR | E37: CCU | F37: 1 pcs | G37: 254 | H37: 0.562 | I37: YM Truth | J37: 44629 | K37: 44630 | M37: 44630 | N37: 44644 | O37: =IF(ISBLANK(N37)=TRUE,TODAY()-J37,N37-J37) -> 15 | P37: 44675 | Q37: 44650 | R37: 44675 | S37: =IF(ISBLANK(R37)=TRUE,TODAY()-J37,R37-J37) -> 46 | AA37: Vessel Delayed at origin
A38: Tallmann | B38: TSL/48748/2200048291 | C38: EXW | D38: TOR | E38: CCU | F38: 2 pcs | G38: 1182 | H38: 1.024 | I38: MSC Valeria | J38: 44631 | K38: 44635 | M38: 44635 | N38: 44636 | O38: =IF(ISBLANK(N38)=TRUE,TODAY()-J38,N38-J38) -> 5 | P38: 44673 | Q38: 44641 | R38: 44673 | S38: =IF(ISBLANK(R38)=TRUE,TODAY()-J38,R38-J38) -> 42 | AA38: Vessel Delayed at origin
A39: Kadant Johnson | B39: TSL/49109/4408511872 | C39: EXW | D39: RTM | E39: CCU | F39: 1 pcs | G39: 267.5 | H39: 0.844 | I39: MSC Irene | J39: 44662 | K39: 44664 | M39: 44665 | N39: 44670 | O39: =IF(ISBLANK(N39)=TRUE,TODAY()-J39,N39-J39) -> 8 | P39: 44688 | Q39: 44679 | R39: 44687 | S39: =IF(ISBLANK(R39)=TRUE,TODAY()-J39,R39-J39) -> 25 | AA39: rebooked by Carrier ex Seamax Fairfield / etd 28.04.2022
A40: ASA Drilling | B40: TSL/49366/2200049228 | C40: EXW | D40: TOR | E40: CCU | F40: 1 pcs | G40: 517 | H40: 0.711 | I40: Maersk Yukon | J40: 44636 | K40: 44655 | M40: 44657 | N40: 44662 | O40: =IF(ISBLANK(N40)=TRUE,TODAY()-J40,N40-J40) -> 26 | P40: 44673 | Q40: 44667 | R40: 44673 | S40: =IF(ISBLANK(R40)=TRUE,TODAY()-J40,R40-J40) -> 37 | AA40: Vessel Delayed at origin
A41: ASA Drilling | B41: TSL/49522/2200049603 | C41: EXW | D41: TOR | E41: CCU | F41: 1 pcs | G41: 318 | H41: 0.474 | I41: Maersk Yukon | J41: 44636 | K41: 44655 | M41: 44657 | N41: 44662 | O41: =IF(ISBLANK(N41)=TRUE,TODAY()-J41,N41-J41) -> 26 | P41: 44673 | Q41: 44667 | R41: 44673 | S41: =IF(ISBLANK(R41)=TRUE,TODAY()-J41,R41-J41) -> 37 | AA41: Vessel Delayed at origin
A42: Reimbold & Strick | C42: CFR | D42: HAM | E42: MAA | F42: 2 pcs | G42: 2131.1 | H42: 2.592 | I42: Herta | J42: 44670 | K42: 44671 | M42: 44673 | N42: 44675 | O42: =IF(ISBLANK(N42)=TRUE,TODAY()-J42,N42-J42) -> 5 | P42: 44687 | Q42: 44684 | R42: 44691 | S42: =IF(ISBLANK(R42)=TRUE,TODAY()-J42,R42-J42) -> 21 | T42: 44693 | X42: 25-0004-205
A43: Framag | B43: TSL/49019/2299901209 | C43: FOB | D43: HAM | E43: CCU | F43: 1 pcs | G43: 730 | H43: 1.54 | I43: MSC Pina | J43: 44658 | K43: 44658 | M43: 44662 | N43: 44671 | O43: =IF(ISBLANK(N43)=TRUE,TODAY()-J43,N43-J43) -> 13 | P43: 44699 | Q43: 44683 | R43: 44699 | S43: =IF(ISBLANK(R43)=TRUE,TODAY()-J43,R43-J43) -> 41 | T43: 44702 | X43: 23-0001-205-00 | AA43: originally booked for MSC Aliya / etd 02.05.2022, vessel delayed/rebooked
A44: Framag | B44: TSL/49018/2299901205 | C44: FOB | D44: HAM | E44: CCU | F44: 1 pcs | G44: 450 | H44: 1.701 | I44: MSC Pina | J44: 44658 | K44: 44658 | M44: 44662 | N44: 44671 | O44: =IF(ISBLANK(N44)=TRUE,TODAY()-J44,N44-J44) -> 13 | P44: 44699 | Q44: 44683 | R44: 44699 | S44: =IF(ISBLANK(R44)=TRUE,TODAY()-J44,R44-J44) -> 41 | T44: 44702 | X44: 23-0002-205-00 | AA44: originally booked for MSC Aliya / etd 02.05.2022, vessel delayed/rebooked
A45: Düsterloh | B45: TSL/48587/2200048212 | C45: EXW | D45: HAM | E45: CCU | F45: 1 pcs | G45: 276 | H45: 0.538 | I45: MSC Pina | J45: 44644 | K45: 44659 | M45: 44664 | N45: 44676 | O45: =IF(ISBLANK(N45)=TRUE,TODAY()-J45,N45-J45) -> 32 | P45: 44699 | Q45: 44688 | R45: 44699 | S45: =IF(ISBLANK(R45)=TRUE,TODAY()-J45,R45-J45) -> 55 | T45: 44702 | X45: 22-0014-205-00 | AA45: late pickup due to Holidays
A46: Eich | B46: TSL/48335/3700839504 - Lot 2 | C46: FOB | D46: HAM | E46: CCU | F46: 1 pcs | G46: 375 | H46: 0.271 | I46: MSC Pina | J46: 44659 | K46: 44665 | M46: 44670 | N46: 44676 | O46: =IF(ISBLANK(N46)=TRUE,TODAY()-J46,N46-J46) -> 17 | P46: 44699 | Q46: 44688 | R46: 44699 | S46: =IF(ISBLANK(R46)=TRUE,TODAY()-J46,R46-J46) -> 40 | T46: 44702 | X46: 22-0015-205-00 | AA46: originally booked for MSC Aliya / etd 07.05.2022, vessel delayed/rebooked
A47: Saacke | B47: TSL/48320/2200047909 | C47: EXW | D47: HAM | E47: CCU | F47: 1 pcs | G47: 682 | H47: 3.648 | I47: MSC Pina | J47: 44671 | K47: 44672 | M47: 44672 | N47: 44676 | O47: =IF(ISBLANK(N47)=TRUE,TODAY()-J47,N47-J47) -> 5 | P47: 44699 | Q47: 44688 | R47: 44699 | S47: =IF(ISBLANK(R47)=TRUE,TODAY()-J47,R47-J47) -> 28 | T47: 44702 | X47: 22-0016-205-00 | AA47: originally booked for MSC Aliya / etd 07.05.2022, vessel delayed/rebooked
A48: Hainzl | B48: TSL/48657/2200048255 | C48: EXW | D48: HAM | E48: CCU | F48: 1 pcs | G48: 1314 | H48: 0.79 | I48: MSC Pina | J48: 44673 | K48: 44676 | M48: 44677 | N48: 44680 | O48: =IF(ISBLANK(N48)=TRUE,TODAY()-J48,N48-J48) -> 7 | P48: 44699 | Q48: 44688 | R48: 44699 | S48: =IF(ISBLANK(R48)=TRUE,TODAY()-J48,R48-J48) -> 26 | T48: 44702 | X48: 22-0017-205-00 | AA48: originally booked for MSC Aliya / etd 07.05.2022, vessel delayed/rebooked
A49: Siebenhaar | B49: TSL/48501/2200048170 | C49: EXW | D49: HAM | E49: CCU | F49: 2 pcs | G49: 810 | H49: 1.536 | I49: MSC Pina | J49: 44677 | K49: 44679 | M49: 44679 | N49: 44683 | O49: =IF(ISBLANK(N49)=TRUE,TODAY()-J49,N49-J49) -> 6 | P49: 44699 | Q49: 44694 | R49: 44699 | S49: =IF(ISBLANK(R49)=TRUE,TODAY()-J49,R49-J49) -> 22 | T49: 44702 | X49: 22-0018-205-00 | AA49: originally booked for MSC Aliya / etd 13.05.2022, vessel delayed/rebooked
A50: Flowserve | B50: TSL/48897/2299901114 | C50: EXW | D50: HAM | E50: CCU | F50: 1 pcs | G50: 732 | H50: 0.806 | I50: MSC Pina | J50: 44678 | K50: 44679 | M50: 44679 | N50: 44683 | O50: =IF(ISBLANK(N50)=TRUE,TODAY()-J50,N50-J50) -> 5 | P50: 44699 | Q50: 44694 | R50: 44699 | S50: =IF(ISBLANK(R50)=TRUE,TODAY()-J50,R50-J50) -> 21 | T50: 44702 | X50: 23-0004-205-00 | AA50: originally booked for MSC Aliya / etd 13.05.2022, vessel delayed/rebooked
A51: SMS | B51: TSL/48479/2200048162 | C51: FOB | D51: HAM | E51: CCU | F51: 1 pcs | G51: 885 | H51: 1.438 | I51: MSC Pina | J51: 44677 | K51: 44678 | N51: 44687 | O51: =IF(ISBLANK(N51)=TRUE,TODAY()-J51,N51-J51) -> 10 | P51: 44699 | Q51: 44694 | R51: 44699 | S51: =IF(ISBLANK(R51)=TRUE,TODAY()-J51,R51-J51) -> 22 | T51: 44702 | X51: 22-0021-205-00 | AA51: originally booked for MSC Aliya / etd 13.05.2022, vessel delayed/rebooked
A52: Eich | B52: TSL/48776/3700844632 | C52: EXW | D52: HAM | E52: CCU | F52: 1 pcs | G52: 720 | H52: 1.099 | I52: MSC Pina | J52: 44677 | K52: 44684 | M52: 44684 | N52: 44686 | O52: =IF(ISBLANK(N52)=TRUE,TODAY()-J52,N52-J52) -> 9 | P52: 44699 | Q52: 44694 | R52: 44699 | S52: =IF(ISBLANK(R52)=TRUE,TODAY()-J52,R52-J52) -> 22 | T52: 44702 | X52: 22-0022-205-00 | AA52: originally booked for MSC Aliya / etd 13.05.2022, vessel delayed/rebooked
A53: Primetals | B53: TSL/49193/2200048917 | C53: EXW | D53: HAM | E53: CCU | F53: 1 pcs | G53: 790 | H53: 2.76 | I53: MSC Pina | J53: 44679 | K53: 44684 | M53: 44686 | N53: 44690 | O53: =IF(ISBLANK(N53)=TRUE,TODAY()-J53,N53-J53) -> 11 | P53: 44699 | Q53: 44694 | R53: 44699 | S53: =IF(ISBLANK(R53)=TRUE,TODAY()-J53,R53-J53) -> 20 | T53: 44702 | X53: 22-0023-205-00 | AA53: originally booked for MSC Aliya / etd 13.05.2022, vessel delayed/rebooked
A54: Watt Drive | B54: TSL/48094/2200047391 | C54: EXW | D54: HAM | E54: CCU | F54: 2 pcs | G54: 1084 | H54: 2.56 | I54: MSC Pina | J54: 44679 | K54: 44684 | M54: 44686 | N54: 44692 | O54: =IF(ISBLANK(N54)=TRUE,TODAY()-J54,N54-J54) -> 13 | P54: 44699 | Q54: 44694 | R54: 44699 | S54: =IF(ISBLANK(R54)=TRUE,TODAY()-J54,R54-J54) -> 20 | T54: 44702 | X54: 22-0024-205-00 | AA54: originally booked for MSC Aliya / etd 13.05.2022, vessel delayed/rebooked
A55: Malmedie | B55: TSL/49927/2200049909 | C55: FOB | D55: HAM | E55: CCU | F55: 1 pcs | G55: 528 | H55: 0.382 | I55: MSC Pina | J55: 44690 | K55: 44690 | N55: 44692 | O55: =IF(ISBLANK(N55)=TRUE,TODAY()-J55,N55-J55) -> 2 | P55: 44699 | Q55: 44694 | R55: 44699 | S55: =IF(ISBLANK(R55)=TRUE,TODAY()-J55,R55-J55) -> 9 | T55: 44702 | X55: 22-0027-205-00 | AA55: originally booked for MSC Aliya / etd 13.05.2022, vessel delayed/rebooked
A56: Primetals / Fossa | B56: TSL/48431/2200048009 | C56: FOB | D56: GEN | E56: CCU | F56: 1 pcs | G56: 5103 | H56: 5.324 | I56: Jebel Ali | J56: 44658 | K56: 44673 | M56: 44680 | N56: 44683 | O56: =IF(ISBLANK(N56)=TRUE,TODAY()-J56,N56-J56) -> 25 | P56: 44700 | Q56: 44673 | R56: 44699 | S56: =IF(ISBLANK(R56)=TRUE,TODAY()-J56,R56-J56) -> 41 | T56: 44707 | X56: 22-0006-205 | AA56: originally booked for ETD 22.04.2022 / vessel delayed
A57: Tenova | B57: TSL/48971/2200048732 | C57: FOB | D57: GEN | E57: CCU | F57: 1 pcs | G57: 260 | H57: 1.55 | I57: Jebel Ali | J57: 44665 | K57: 44671 | N57: 44683 | O57: =IF(ISBLANK(N57)=TRUE,TODAY()-J57,N57-J57) -> 18 | P57: 44700 | Q57: 44673 | R57: 44699 | S57: =IF(ISBLANK(R57)=TRUE,TODAY()-J57,R57-J57) -> 34 | T57: 44707 | X57: 22-0005-205 | AA57: originally booked for ETD 22.04.2022 / vessel delayed
A58: Imequadri | B58: TSL/48843/2299900867 | C58: EXW | D58: GEN | E58: CCU | F58: 1 pcs | G58: 900 | H58: 4.25 | I58: Jebel Ali | J58: 44673 | K58: 44679 | M58: 44680 | N58: 44684 | O58: =IF(ISBLANK(N58)=TRUE,TODAY()-J58,N58-J58) -> 11 | P58: 44700 | Q58: 44690 | R58: 44699 | S58: =IF(ISBLANK(R58)=TRUE,TODAY()-J58,R58-J58) -> 26 | T58: 44701 | X58: 23-0003-205 | AA58: originally booked for ETD 09.05.2022 / vessel delayed
A59: Cosil | B59: TSL/49134/2200048929 | C59: EXW | D59: GEN | E59: CCU | F59: 1 pcs | G59: 410 | H59: 0.576 | I59: Jebel Ali | J59: 44672 | K59: 44678 | M59: 44680 | N59: 44683 | O59: =IF(ISBLANK(N59)=TRUE,TODAY()-J59,N59-J59) -> 11 | P59: 44700 | Q59: 44690 | R59: 44699 | S59: =IF(ISBLANK(R59)=TRUE,TODAY()-J59,R59-J59) -> 27 | T59: 44701 | X59: 22-0012-205 | AA59: originally booked for ETD 09.05.2022 / vessel delayed
A60: EM Moulds | B60: TSL/49526/2200048854 | C60: FOB | D60: GEN | E60: CCU | F60: 1 pcs | G60: 965 | H60: 0.743 | I60: Paris Express | J60: 44673 | K60: 44690 | M60: 44691 | N60: 44694 | O60: =IF(ISBLANK(N60)=TRUE,TODAY()-J60,N60-J60) -> 21 | P60: 44701 | Q60: 44695 | R60: 44704 | S60: =IF(ISBLANK(R60)=TRUE,TODAY()-J60,R60-J60) -> 31 | T60: 44714 | X60: 22-0001-206 | AA60: originally booked for ETD 14.05.2022 / vessel delayed
A61: Specialtrafo | B61: TSL/49346/2200049312 | C61: EXW | D61: GEN | E61: CCU | F61: 1 pcs | G61: 1500 | H61: 7.905 | I61: 44701 | J61: 44683 | K61: 44684 | M61: 44686 | N61: 44686 | O61: =IF(ISBLANK(N61)=TRUE,TODAY()-J61,N61-J61) -> 3 | P61: 44701 | Q61: 44695 | R61: 44704 | S61: =IF(ISBLANK(R61)=TRUE,TODAY()-J61,R61-J61) -> 21 | T61: 44714 | X61: 22-0002-206 | AA61: originally booked for ETD 14.05.2022 / vessel delayed
A62: Maina | B62: TSL/48851/2299901022 | C62: FOB | D62: GEN | E62: CCU | F62: 3 pcs | G62: 1403 | H62: 1.536 | I62: 44732 | J62: 44678 | K62: 44680 | M62: 44683 | N62: 44693 | O62: =IF(ISBLANK(N62)=TRUE,TODAY()-J62,N62-J62) -> 15 | P62: 44701 | Q62: 44695 | R62: 44704 | S62: =IF(ISBLANK(R62)=TRUE,TODAY()-J62,R62-J62) -> 26 | T62: 44714 | X62: 23-0001-206 | AA62: originally booked for ETD 14.05.2022 / vessel delayed
A63: BSA | B63: TCI/918/4300000963 | C63: FOB | D63: GEN | E63: CCU | F63: 1 pcs | G63: 1192 | H63: 0.726 | I63: One Mackinac | J63: 44692 | K63: 44693 | M63: 44694 | N63: 44698 | O63: =IF(ISBLANK(N63)=TRUE,TODAY()-J63,N63-J63) -> 6 | P63: 44707 | Q63: 44707 | R63: 44712 | S63: =IF(ISBLANK(R63)=TRUE,TODAY()-J63,R63-J63) -> 20 | T63: 44714 | X63: 23-0002-206 | AA63: vessel delayed
A64: Vibrazioni | B64: TSL/49815/2200049937 | C64: EXW | D64: GEN | E64: CCU | F64: 1 pcs | G64: 360 | H64: 0.796 | I64: ONE Mackinac | J64: 44693 | K64: 44694 | N64: 44698 | O64: =IF(ISBLANK(N64)=TRUE,TODAY()-J64,N64-J64) -> 5 | P64: 44707 | Q64: 44707 | R64: 44712 | S64: =IF(ISBLANK(R64)=TRUE,TODAY()-J64,R64-J64) -> 19 | T64: 44714 | X64: 22-0003-206 | AA64: vessel delayed
A65: Mi-Jack | B65: TSL/48690/2200047851 | C65: EXW | D65: NYC | E65: CCU | F65: 2 pcs | G65: 803.8 | H65: 1.595 | I65: APL Sentosa | J65: 44655 | K65: 44656 | M65: 44656 | N65: 44659 | O65: =IF(ISBLANK(N65)=TRUE,TODAY()-J65,N65-J65) -> 4 | P65: 44694 | Q65: 44681 | R65: 44696 | S65: =IF(ISBLANK(R65)=TRUE,TODAY()-J65,R65-J65) -> 41 | T65: 44700 | X65: 22-0005-206 | AA65: vessel is delayed
A66: Sarclad | B66: TICRC/1570/2200049378 | C66: EXW | D66: LON | E66: NSA | F66: 1 pcs | G66: 840 | H66: 2.295 | I66: MSC Jersey | J66: 44690 | K66: 44691 | M66: 44692 | N66: 44694 | O66: =IF(ISBLANK(N66)=TRUE,TODAY()-J66,N66-J66) -> 4 | P66: 44697 | Q66: 44697 | R66: 18.0.2022 | S66: =IF(ISBLANK(R66)=TRUE,TODAY()-J66,R66-J66) -> #VALUE! | T66: 44705 | X66: 23-0005-205 | AA66: vessel is delayed
A67: Tallmann | B67: TSL/48748/2200048291 | C67: EXW | D67: TOR | E67: CCU | F67: 2 pcs | G67: 1168 | H67: 1.012 | I67: Maersk Guayaquil | J67: 44662 | K67: 44670 | M67: 44671 | N67: 44671 | O67: =IF(ISBLANK(N67)=TRUE,TODAY()-J67,N67-J67) -> 9 | P67: 44689 | Q67: 44689 | R67: 44673 | S67: =IF(ISBLANK(R67)=TRUE,TODAY()-J67,R67-J67) -> 11 | T67: 44699 | X67: 22-0011-205 | AA67: vessel is delayed
A68: Schneider | C68: CFR | D68: HAM | E68: NIN | F68: 1 pcs | G68: 100 | H68: 0.432 | I68: Cosco Pride | J68: 44650 | K68: 44665 | N68: 44662 | O68: =IF(ISBLANK(N68)=TRUE,TODAY()-J68,N68-J68) -> 12 | P68: 44695 | Q68: 44691 | R68: 44693 | S68: =IF(ISBLANK(R68)=TRUE,TODAY()-J68,R68-J68) -> 43 | T68: 44697 | X68: 25-0003-205 | AA68: vessel is delayed
A69: Europlast | C69: CFR | D69: HAM | E69: KBL | F69: 1 pcs | G69: 465 | H69: 1.104 | I69: Al Nefud | J69: 44686 | K69: 44687 | M69: 44690 | N69: 44692 | O69: =IF(ISBLANK(N69)=TRUE,TODAY()-J69,N69-J69) -> 6 | P69: 44699 | Q69: 44699 | R69: 44695 | S69: =IF(ISBLANK(R69)=TRUE,TODAY()-J69,R69-J69) -> 9 | T69: 44700 | X69: 25-0014-205 | AA69: vessel is delayed
A70: SIJ Ravne | B70: TSL/50091/4408462148 | C70: EXW | D70: HAM | E70: CCU | F70: 4 pcs | G70: 538 | H70: 0.087 | J70: 44671 | K70: 44677 | M70: 44678 | O70: =IF(ISBLANK(N70)=TRUE,TODAY()-J70,N70-J70) -> 1434 | P70: 44694 | Q70: 44694 | S70: =IF(ISBLANK(R70)=TRUE,TODAY()-J70,R70-J70) -> 1434 | X70: 22-0019-205-00 | AA70: changed to AIR
A71: Ingelia SL | B71: TSL/50264/2200050419 | C71: EXW | D71: BCN | E71: CCU | F71: 1PAL | G71: 1018 | H71: 1.804 | I71: Alula Express | J71: 44700 | K71: 44712 | M71: 44712 | N71: 44713 | O71: =IF(ISBLANK(N71)=TRUE,TODAY()-J71,N71-J71) -> 13 | P71: 44725 | Q71: 44725 | R71: 44725 | S71: =IF(ISBLANK(R71)=TRUE,TODAY()-J71,R71-J71) -> 25 | T71: 44726 | X71: 22-0009-206 | AA71: BCNCCU2405943V
A72: Ingersoll | B72: TSL/48486/2200048171 | C72: EXW | D72: SF | E72: CCU | F72: 1 pcs | G72: 1180 | H72: 5.621 | I72: ONE Arcadia | J72: 44645 | K72: 44702 | N72: 44704 | O72: =IF(ISBLANK(N72)=TRUE,TODAY()-J72,N72-J72) -> 59 | P72: 44718 | Q72: 44714 | R72: 44718 | S72: =IF(ISBLANK(R72)=TRUE,TODAY()-J72,R72-J72) -> 73 | T72: 44728 | X72: 22-0028-206 | AA72: delayed by supplier for quality reasons / correction on docs required
A73: ASA Drilling | B73: TSL/49684/2200049816 | C73: EXW | D73: TOR | E73: CCU | F73: 1 pcs | G73: 661 | H73: 0.435 | I73: Gunvor Maersk | J73: 44670 | K73: 44692 | M73: 44693 | N73: 44694 | O73: =IF(ISBLANK(N73)=TRUE,TODAY()-J73,N73-J73) -> 24 | P73: 44728 | Q73: 44706 | R73: 44719 | S73: =IF(ISBLANK(R73)=TRUE,TODAY()-J73,R73-J73) -> 49 | T73: 44733 | X73: 22-0024-206
A74: ASA Drilling | B74: TSL/49979/2200050144 | C74: EXW | D74: TOR | E74: CCU | F74: 1 pcs | G74: 250 | H74: 0.44 | I74: Gunvor Maersk | J74: 44690 | K74: 44692 | M74: 44693 | N74: 44694 | O74: =IF(ISBLANK(N74)=TRUE,TODAY()-J74,N74-J74) -> 4 | P74: 44728 | Q74: 44706 | R74: 44719 | S74: =IF(ISBLANK(R74)=TRUE,TODAY()-J74,R74-J74) -> 29 | T74: 44733 | X74: 22-0025-206
A75: Pyrotek | B75: TSL/2200048615 | C75: FCA | D75: MTR | E75: CCU | F75: 6 pcs | G75: 2121 | H75: 3.095 | I75: Gunvor Maersk | J75: 44677 | K75: 44694 | M75: 44691 | N75: 44694 | O75: =IF(ISBLANK(N75)=TRUE,TODAY()-J75,N75-J75) -> 17 | P75: 44728 | Q75: 44706 | R75: 44719 | S75: =IF(ISBLANK(R75)=TRUE,TODAY()-J75,R75-J75) -> 42 | T75: 44734
A76: Tallmann | B76: TSL/48992/2200048516 | C76: EXW | D76: TOR | E76: CCU | F76: 3 pcs | G76: 1563 | H76: 1.68 | I76: Gunvor Maersk | J76: 44673 | K76: 44689 | M76: 44691 | N76: 44694 | O76: =IF(ISBLANK(N76)=TRUE,TODAY()-J76,N76-J76) -> 21 | P76: 44728 | Q76: 44706 | R76: 44719 | S76: =IF(ISBLANK(R76)=TRUE,TODAY()-J76,R76-J76) -> 46 | T76: 44735 | X76: 22-0006-206
A77: Metso | B77: TSL/48419/2200047846 | C77: EXW | D77: HAM | E77: CCU | F77: 2 pcs | G77: 1419 | H77: 0.522 | I77: Northern Justice | J77: 44686 | K77: 44690 | M77: 44693 | N77: 44698 | O77: =IF(ISBLANK(N77)=TRUE,TODAY()-J77,N77-J77) -> 12 | P77: 44737 | Q77: 44712 | R77: 44737 | S77: =IF(ISBLANK(R77)=TRUE,TODAY()-J77,R77-J77) -> 51 | T77: 44740 | X77: 22-0010-206
A78: Binder | B78: TSL/49821/2200049768 | C78: EXW | D78: HAM | E78: CCU | F78: 2 pcs | G78: 727 | H78: 1.018 | I78: Northern Justice | J78: 44691 | K78: 44691 | M78: 44694 | N78: 44701 | O78: =IF(ISBLANK(N78)=TRUE,TODAY()-J78,N78-J78) -> 10 | P78: 44737 | Q78: 44712 | R78: 44737 | S78: =IF(ISBLANK(R78)=TRUE,TODAY()-J78,R78-J78) -> 46 | T78: 44740 | X78: 22-0011-206
A79: RHI | B79: TSL/2200049037 | C79: FOB | D79: HAM | E79: CCU | F79: 1 pcs | G79: 1242 | H79: 1 | I79: Northern Justice | J79: 44692 | K79: 44693 | N79: 44699 | O79: =IF(ISBLANK(N79)=TRUE,TODAY()-J79,N79-J79) -> 7 | P79: 44737 | Q79: 44712 | R79: 44737 | S79: =IF(ISBLANK(R79)=TRUE,TODAY()-J79,R79-J79) -> 45 | T79: 44740 | X79: 22-0019-206
A80: Reinguss | B80: TSL/49234/2200048947 | C80: FOB | D80: HAM | E80: CCU | F80: 1 pcs | G80: 1410 | H80: 3.553 | I80: Northern Justice | J80: 44692 | K80: 44697 | N80: 44701 | O80: =IF(ISBLANK(N80)=TRUE,TODAY()-J80,N80-J80) -> 9 | P80: 44737 | Q80: 44712 | R80: 44737 | S80: =IF(ISBLANK(R80)=TRUE,TODAY()-J80,R80-J80) -> 45 | T80: 44740 | X80: 22-0021-206
A81: UHT | B81: TSL/2200050195 | C81: EXW | D81: HAM | E81: CCU | F81: 2 pcs | G81: 2386 | H81: 2.439 | I81: Northern Justice | J81: 44692 | K81: 44693 | M81: 44694 | N81: 44701 | O81: =IF(ISBLANK(N81)=TRUE,TODAY()-J81,N81-J81) -> 9 | P81: 44737 | Q81: 44712 | R81: 44737 | S81: =IF(ISBLANK(R81)=TRUE,TODAY()-J81,R81-J81) -> 45 | T81: 44740 | X81: 22-0020-206
A82: Alpine Metal Tech | B82: TSL/49489/2200049554 | C82: EXW | D82: HAM | E82: CCU | F82: 1 pcs | G82: 309 | H82: 0.647 | I82: Northern Justice | J82: 44698 | K82: 44694 | M82: 44697 | N82: 44701 | O82: =IF(ISBLANK(N82)=TRUE,TODAY()-J82,N82-J82) -> 3 | P82: 44737 | Q82: 44712 | R82: 44737 | S82: =IF(ISBLANK(R82)=TRUE,TODAY()-J82,R82-J82) -> 39 | T82: 44740 | X82: 22-0013-206
A83: ZwickRoell | B83: TSL/49282/2400002273 | C83: EXW | D83: HAM | E83: CCU | F83: 1 pcs | G83: 445 | H83: 2.108 | I83: Northern Justice | J83: 44699 | K83: 44694 | M83: 44697 | N83: 44701 | O83: =IF(ISBLANK(N83)=TRUE,TODAY()-J83,N83-J83) -> 2 | P83: 44737 | Q83: 44712 | R83: 44737 | S83: =IF(ISBLANK(R83)=TRUE,TODAY()-J83,R83-J83) -> 38 | T83: 44740 | X83: 22-0014-206
A84: Malmedie | B84: TSL/49931/2200050143 | C84: FOB | D84: HAM | E84: CCU | F84: 2 pcs | G84: 1317 | H84: 1.242 | I84: Northern Justice | J84: 44694 | K84: 44697 | N84: 44705 | O84: =IF(ISBLANK(N84)=TRUE,TODAY()-J84,N84-J84) -> 11 | P84: 44737 | Q84: 44723 | R84: 44737 | S84: =IF(ISBLANK(R84)=TRUE,TODAY()-J84,R84-J84) -> 43 | T84: 44740 | X84: 22-0012-206
A85: SMS | B85: TSL/47952/2200047396 | C85: FOB | D85: HAM | E85: CCU | F85: 2 pcs | G85: 3905 | H85: 4.32 | I85: Northern Justice | J85: 44700 | K85: 44693 | N85: 44706 | O85: =IF(ISBLANK(N85)=TRUE,TODAY()-J85,N85-J85) -> 6 | P85: 44737 | Q85: 44723 | R85: 44737 | S85: =IF(ISBLANK(R85)=TRUE,TODAY()-J85,R85-J85) -> 37 | T85: 44740 | X85: 22-0015-206
A86: Eich | B86: TSL/48301/2200047899 | C86: EXW | D86: HAM | E86: CCU | F86: 4pcs | G86: 3220 | H86: 3.315 | I86: Northern Justice | J86: 44704 | K86: 44700 | M86: 44704 | N86: 44711 | O86: =IF(ISBLANK(N86)=TRUE,TODAY()-J86,N86-J86) -> 7 | P86: 44737 | Q86: 44723 | R86: 44737 | S86: =IF(ISBLANK(R86)=TRUE,TODAY()-J86,R86-J86) -> 33 | T86: 44740 | X86: 22-0016-206
A87: AlpineMetal | B87: TSL/49221/2299901065 | C87: FOB | D87: HAM | E87: CCU | F87: 1CS | G87: 4700 | H87: 10.67 | I87: Northern Justice | J87: 44706 | K87: 44711 | N87: 44714 | O87: =IF(ISBLANK(N87)=TRUE,TODAY()-J87,N87-J87) -> 8 | P87: 44737 | Q87: 44723 | R87: 44737 | S87: =IF(ISBLANK(R87)=TRUE,TODAY()-J87,R87-J87) -> 31 | T87: 44740 | X87: 23-0003-206
A88: SMS | B88: TSL/49430/4408538305 | C88: FOB | D88: HAM | E88: CCU | F88: 2pcs | G88: 280 | H88: 0.814 | I88: Northern Justice | J88: 44708 | K88: 44711 | N88: 44713 | O88: =IF(ISBLANK(N88)=TRUE,TODAY()-J88,N88-J88) -> 5 | P88: 44737 | Q88: 44723 | R88: 44737 | S88: =IF(ISBLANK(R88)=TRUE,TODAY()-J88,R88-J88) -> 29 | T88: 44740 | X88: 22-0017-206
A89: SIJ Ravne | B89: TSL/49172/2200048979 | C89: EXW | D89: HAM | E89: CCU | F89: 8 pcs | G89: 1480 | H89: 0.068 | I89: Northern Justice | J89: 44677 | K89: 44680 | M89: 44684 | N89: 44692 | O89: =IF(ISBLANK(N89)=TRUE,TODAY()-J89,N89-J89) -> 15 | P89: 44737 | Q89: 44723 | R89: 44737 | S89: =IF(ISBLANK(R89)=TRUE,TODAY()-J89,R89-J89) -> 60 | T89: 44740 | X89: 22-0022-206 | AA89: Damage
A90: SMS | B90: TSL/48302/2200047901 | C90: FOB | D90: HAM | E90: CCU | F90: 2 pcs | G90: 1055 | H90: 2.604 | I90: CMA CGM Louvre | J90: 44712 | K90: 44713 | N90: 44714 | O90: =IF(ISBLANK(N90)=TRUE,TODAY()-J90,N90-J90) -> 2 | P90: 44741 | Q90: 44731 | R90: 44741 | S90: =IF(ISBLANK(R90)=TRUE,TODAY()-J90,R90-J90) -> 29 | T90: 44743 | X90: 22-0026-206 | AA90: vessel delayed by congested port
A91: Josua CORTS | B91: TSL/48874/2299901202 | C91: FOB | D91: HAM | E91: CCU | F91: 4 pcs | G91: 3382 | H91: 1.034 | I91: CMA CGM Louvre | J91: 44700 | K91: 44719 | M91: 44719 | N91: 44721 | O91: =IF(ISBLANK(N91)=TRUE,TODAY()-J91,N91-J91) -> 21 | P91: 44741 | Q91: 44731 | R91: 44741 | S91: =IF(ISBLANK(R91)=TRUE,TODAY()-J91,R91-J91) -> 41 | T91: 44743 | X91: 23-0004-206 | AA91: vessel delayed by congested port
A92: Durko Dakovic | B92: TSL/49842/2200049322 | C92: FOB | D92: HAM | E92: CCU | F92: 1 pcs | G92: 1568 | H92: 2.66 | I92: CMA CGM Louvre | J92: 44708 | K92: 44712 | N92: 44727 | O92: =IF(ISBLANK(N92)=TRUE,TODAY()-J92,N92-J92) -> 19 | P92: 44741 | Q92: 44731 | R92: 44741 | S92: =IF(ISBLANK(R92)=TRUE,TODAY()-J92,R92-J92) -> 33 | T92: 44743 | X92: 23-0005-206 | AA92: vessel delayed by congested port
A93: Bremskerl | B93: TSL/49608/2200049362 | C93: EXW | D93: HAM | E93: CCU | F93: 16 pcs | G93: 4628 | H93: 11.539 | I93: CMA CGM Louvre | J93: 44713 | K93: 44719 | M93: 44720 | N93: 44721 | O93: =IF(ISBLANK(N93)=TRUE,TODAY()-J93,N93-J93) -> 8 | P93: 44741 | Q93: 44731 | R93: 44741 | S93: =IF(ISBLANK(R93)=TRUE,TODAY()-J93,R93-J93) -> 28 | T93: 44743 | X93: 22-0027-206 | AA93: vessel delayed by congested port
A94: ZwickRoell | B94: TSL/49255/2400002274 | C94: EXW | D94: HAM | E94: CCU | F94: 2pcs | G94: 2925 | H94: 6.825 | I94: CMA CGM Louvre | J94: 44704 | K94: 44706 | M94: 44720 | N94: 44722 | O94: =IF(ISBLANK(N94)=TRUE,TODAY()-J94,N94-J94) -> 18 | P94: 44741 | Q94: 44731 | R94: 44741 | S94: =IF(ISBLANK(R94)=TRUE,TODAY()-J94,R94-J94) -> 37 | T94: 44743 | X94: 22-0018-206 | AA94: vessel delayed by congested port
A95: Reimbold & Strick | C95: CFR | D95: HAM | E95: AHM | F95: 1 pcs | G95: 672.7 | H95: 0.969 | I95: Prague Express | J95: 44722 | K95: 44725 | M95: 44726 | N95: 44726 | O95: =IF(ISBLANK(N95)=TRUE,TODAY()-J95,N95-J95) -> 4 | P95: 44745 | Q95: 44735 | R95: 44745 | S95: =IF(ISBLANK(R95)=TRUE,TODAY()-J95,R95-J95) -> 23 | T95: 44747 | X95: 25-0001-207 | AA95: vessel delayed by congested port
A96: Ebner | B96: TSL/49270/2499900028 | C96: FOB | D96: HAM | E96: NSA | F96: 4 pcs | G96: 3300 | H96: 8.72 | I96: Prague Express | J96: 44687 | K96: 44714 | N96: 44721 | O96: =IF(ISBLANK(N96)=TRUE,TODAY()-J96,N96-J96) -> 34 | P96: 44745 | Q96: 44735 | R96: 44745 | S96: =IF(ISBLANK(R96)=TRUE,TODAY()-J96,R96-J96) -> 58 | T96: 44747 | X96: 22-0002-207 | AA96: vessel delayed by congested port
A97: ZwickRoell | B97: TSL/49164/2400002278 | C97: FOB | D97: HAM | E97: NSA | F97: 1 pcs | G97: 1190 | H97: 4.313 | I97: Prague Express | J97: 44714 | K97: 44720 | M97: 44720 | N97: 44722 | O97: =IF(ISBLANK(N97)=TRUE,TODAY()-J97,N97-J97) -> 8 | P97: 44745 | Q97: 44735 | R97: 44745 | S97: =IF(ISBLANK(R97)=TRUE,TODAY()-J97,R97-J97) -> 31 | T97: 44747 | X97: 22-0001-207 | AA97: vessel delayed by congested port
A98: Eich | B98: TSL/49268/2200049120 | C98: EXW | D98: HAM | E98: CCU | F98: 1 pcs | G98: 877 | H98: 0.767 | I98: CMA CGM Concorde | J98: 44740 | K98: 44743 | M98: 44746 | N98: 44747 | O98: =IF(ISBLANK(N98)=TRUE,TODAY()-J98,N98-J98) -> 7 | P98: 44769 | Q98: 44764 | S98: =IF(ISBLANK(R98)=TRUE,TODAY()-J98,R98-J98) -> 1365 | X98: 22-0017-207 | AA98: Switched into Airfreight 07.07.2022
A99: EM Moulds | B99: TSL/49526/2200048854 | C99: FOB | D99: GEN | E99: CCU | F99: 1 pcs | G99: 966 | H99: 0.795 | I99: Milano Bridge | J99: 44732 | K99: 44734 | M99: 44735 | N99: 44739 | O99: =IF(ISBLANK(N99)=TRUE,TODAY()-J99,N99-J99) -> 7 | P99: 44747 | Q99: 44742 | R99: 44750 | S99: =IF(ISBLANK(R99)=TRUE,TODAY()-J99,R99-J99) -> 18 | T99: 44754 | X99: 22-0010-207 | AA99: vessel delayed by congested port
A100: Thermocast | B100: TSL/49550/2200049582 | C100: FOB | D100: GEN | E100: CCU | F100: 1 pcs | G100: 1620 | H100: 2.142 | I100: Milano Bridge | J100: 44734 | K100: 44735 | N100: 44739 | O100: =IF(ISBLANK(N100)=TRUE,TODAY()-J100,N100-J100) -> 5 | P100: 44747 | Q100: 44742 | R100: 44750 | S100: =IF(ISBLANK(R100)=TRUE,TODAY()-J100,R100-J100) -> 16 | T100: 44754 | X100: 22-0011-207 | AA100: vessel delayed by congested port
...

Sheet Useful
C2: EXIT CUSTOMS CODE HAMBURG= DE/004851
C5: CUSTOMS EXIT - Barcelona / code : ES000812
H7: Cnee/Notify | M7: TATA Steel Ltd
C8: Shipper: | F8: Cnee/Notify | H8: TKM GLOBAL LOGISTICS LTD | M8: IEC Code: 0388039124
C9: TKM Global GmbH | F9: TKM Global Logistics Ltd | H9: EVEREST CHAMBER, B-206, MATHURADAS VASANJI RD,
C10: Esplanade 41 | F10: Infinity IT Lagoon | H10: NEAR MAROL METRO STATION, ANDHER EAST,
C11: 20354 Hamburg, Germany | F11: 7th Floor, Sector V, Bidhannagar | H11: MUMBAI- 400059, MAHARASHTRA, INDIA | M11: TKM Global GmbH
F12: 700091 Kolkata, India | H12: PAN: AABCT2426M | M12: EORI: DE3236978
F13: GST 19AABCT2426M1Z4 | H13: GST: 27AABCT2426M1Z7
F14: PAN: AABCT2426M | H14: Janhavi@tkmglobal.com
F15: TKMCCU@TkmGlobal.com | H15: CELL: +91 9833407164
F16: CONTACT: PARTHA DAS +91 98311 17122
C17: Freight Prepaid | F17: PARTHA@TKMGLOBAL.COM
C18: Express B/L
H19: 1.ONE ORPHEUS 075W=ETD-08.12.25
C20: Marks: | D20: 5 cases | F20: 99.344KGS | G20: 19,984cbm | H20: 2.ONE HAMBURG / 083W=ETD- 18.11.25
C21: TATA Steel Limited | F21: s.t.c. | H21: 3.ONE OLYMPUS / 079W=ETD-24.12.25
C22: TSL/49567/2200049440 | F22: 1 Set Spare
F23: Pressurization Valve, Hot Stove
F24: Inv.: 37001608
F25: HS-Code: 84818085
C26: Marks: | D26: 2 cases | F26: 1540,0KGS | G26: 3,063cbm
C27: Jindal Steel & Power Ltd | F27: s.t.c.
C28: 4561104547 | F28: Supply of Lance Tips as per
F29: PO NO: 4561104547 DTD 03.09.2022
F30: TERMS CIF Kolkata Seaport in India
F31: Incoterms 2020
F32: HS-Code: 84179000
C33: Marks: | D33: 7 cases | F33: 11.080,0KGS | G33: 11,660cbm
C34: TATA Steel Limited | F34: s.t.c.
C35: TSL/49463/2200049473 | F35: Bearing Retainer
F36: Sleeving Ring Unit
F37: Sleeve Unit
F38: Inv.: 60171691 + 60171689
F39: HS-Code: 84559000
C40: Marks: | D40: 1 case | F40: 153,0KGS | G40: 0,384cbm
C41: TATA Steel Limited | F41: s.t.c.
C42: TSL/49787/2200050004 | F42: Universal Compensator DN 200
F43: Inv.: 260147
F44: HS-Code: 83071000
